Workbook
Name Additional_ITC_Basis_Reducer_Fine_Tuning: Dashboard!$H$48
Name Aggregate_Construction_Cost: Dashboard!$E$32
Name Aggregate_Project_Cost: Dashboard!$E$39
Name Cash_Equity_Investment_Share: Dashboard!$H$63
Name Cash_Equity_Post_Flip_Share: Dashboard!$H$61
Name Cash_Equity_Pre_Flip_Share: Dashboard!$H$59
Name Cash_on_Cash_Return_Premium: Dashboard!$H$66
Name Construction_Loan_Amount: Dashboard!$H$19
Name Construction_Loan_Fee: Dashboard!$H$21
Name Construction_Loan_Rate: Dashboard!$H$20
Name Construction_Loan_Term: Dashboard!$H$18
Name Construction_Loan?: Dashboard!$H$17
Name Customer_Dem_Charge_Percent: Dashboard!$E$43
Name Customer_Discount_Rate: Dashboard!$E$46
Name Customer_Monthly_kWh_Usage: Dashboard!$E$45
Name Customer_Utility_Charge_Escalator: Dashboard!$E$44
Name Customer_Utility_Charge_kWh: Dashboard!$E$42
Name Depreciation_Basis: Dashboard!$E$51
Name Depreciation_Bonus_Rate: Dashboard!$H$37
Name Depreciation_Methodology?: Dashboard!$H$36
Name Depreciation_Table: Dashboard!$B$54:$E$59
Name Equity_Investment: Dashboard!$H$24
Name Fed._ITC_Eligible_Property_Value: Dashboard!$H$49
Name Federal_ITC_Cash_Sale_OnOff: Dashboard!$H$40
Name Federal_ITC_Dollar_Value: Dashboard!$H$50
Name Federal_ITC_Rate: Dashboard!$H$41
Name Insurance_Cost_Escalator: Dashboard!$K$44
Name Insurance_Cost_per_Watt_DC: Dashboard!$K$43
Name Interconnection_Costs: Dashboard!$E$34
Name Investor_Discount_Rate: Dashboard!$H$25
Name Investor_Target_Flip_IRR: Dashboard!$H$65
Name ITC_Cash_Sale_Discount_to_Purchase_Price: Dashboard!$H$42
Name ITC_Cash_Sale_First_Year_Payment: Dashboard!$H$44
Name ITC_Cash_Sale_Number_of_Annual_Payments: Dashboard!$H$43
Name ITC_Eligible_Property_Value: Dashboard!$H$49
Name Manual_Entry_Estimated_P50_Production: Dashboard!$E$25
Name Mgt._Fee__Share__of_Remaining_Cash_Flow: Dashboard!$H$67
Name OandM_Cost_Escalator: Dashboard!$K$42
Name OandM_Cost_per_W_DC: Dashboard!$K$41
Name Other_Closing_Costs_Fees: Dashboard!$E$38
Name Owner_is_Taxpayer_Non_Taxpayer?: Dashboard!$H$34
Name P50_Production_1st_Yr: Dashboard!$E$28
Name P95_Production_1st_Yr: Dashboard!$E$29
Name Panel_Degradation_Rate: Dashboard!$E$26
Name PPA_Price_Annual_Escalator: Dashboard!$K$18
Name PPA_Price_kWh: Dashboard!$K$17
Name Production_Delta_P95_P50: Dashboard!$E$27
Name Project_Debt?: Dashboard!$H$27
Name Project_Loan_Amount: Dashboard!$H$30
Name Project_Loan_Coverage_Ratio: Dashboard!$H$31
Name Project_Loan_Debt_Equity_Ratio: Dashboard!$H$32
Name Project_Loan_Rate: Dashboard!$H$29
Name Project_Loan_Term?: Dashboard!$H$28
Name Project_Net_Investment: Dashboard!$H$24
Name Project_Sale_Price: Dashboard!$H$23
Name Property_Equip_Base_Value: Dashboard!$K$30
Name Property_Equip_Book_Adj_Rate: Dashboard!$K$31
Name Property_Equip_Tax_Rate: Dashboard!$K$29
Name Property_Site_Base_Value: Dashboard!$K$27
Name Property_Site_Tax_Rate: Dashboard!$K$26

Sheet Overview
F3: PROPRIETARY AND CONFIDENTIAL
F5: Cautionary Note
F6: "This model is provided for illustration purposes only. Before using to evaluate any project, it should be audited to ensure functionality and accuracy, and to adapt the model to meet the specific requirements of applicable political and utility authorities, as well as any prospective customer, developer, EPC Contractor, investor, purchaser or lender. This model should not be used as tax advice. You should consult an accounting professional to determine if your specific circumstances allow you to be eligible for all of the credits/benefits demonstrated."
B15: Last Change
B16: Last Change Date
B18: Copyright, 2020 & 2022; All rights reserved by CapIron, Inc. This model may not be sold, licensed or distributed without the prior written approval of CapIron, Inc. DOE Solar District Cup Competitors may use this model for the competition and personal use only.
E23: Demo Solar PV Model v2.1
E25: Illustrative Distributed Generation Solar PV Financial Model
E27: Cautionary Note
E28: This Distributed Generation Solar PV Financial Model for a Solar PV Project has been created to help understand the static and dynamic issues involved in building, financing and operating distributed generation solar PV projects for illustrative purposes only. The data and analysis in this model are not intended as representations or warranties as to how actual distributed generation solar PV projects will, could or should perform. Any prospective customer, developer, EPC Contractor, investor, purchaser or lender should not rely on this model for investment or tax advice, but should perform their own due diligence and analysis, and consult their own business, investment, legal and tax advisors to determine the suitability and potential of any investment in such a business for their particular circumstances.
B30: DATA KEY | C30: Drop Down Menu | E30: Important User Note
C31: Input Variable | E31: No Worksheets or cells are presently protected against change, whether intended or unintended.
C32: Calculated
E33: All changes to this model should be limited to the input variable boxes and drop down menu boxes, each color-coded as noted on the key to the left. Changes should not be entered into any white-colored boxes, as these numbers are hard coded, and are intended to remain fixed ratios, constant cell references or constant numbers. Changing a hard coded, white box will lead to unpredictable errors and compromise the value of this model.
E35: Purpose
E36: This Workbook is designed to help a developer identify solar project opportunities and understand whether the project is buildable, economically valuable to the power offtake and strong enough to attract financing if needed. The model requires inputs specific to the project, but is intended to be used in an iterative fashion so that as the solar project advances, new and more accurate inputs can be added to clarify the prospective project returns. The model can be used and adapted for C&I projects and small utility-scale solar PV projects.
E38: Organization
E39: This Workbook is organized as an active model of the project economics for a proposed distributed generation solar PV project. The Worksheets are all linked so that each should rely on the same common data to produce a consistent result.
E41: Inputs & Outputs
E42: The Inputs & Outputs worksheet operates as a control panel - it sets forth on the top left of the worksheet the principal input variables that most users will wish to explore or understand. Directly to the right of this Inputs section is the Outputs section. This section consists of a series of charts and a table to show how changes in the Inputs could affect key performance parameters of the project, including cash flows, NPV and IRR.
E44: Unstructured
E45: The Unstructured worksheet shows the economics for the Projects as held by a single tax investor, and allows the User through the Inputs & Outputs worksheet to toggle among internally tax efficient (State and Federal), partially tax efficient (Federal only) and inefficient (State and Federal).
E47: Partnership Flip
E48: The Partnership Flip worksheet shows the economics for a simple yield-based partnership flip model. The model provides for a cash waterfall, followed by an allocation of the remaining cash and all of the tax benefits pursuant to a set ratio (e.g., 95 to 5) that favors the tax investor over the non-tax (cash equity) investor. When the tax investor's return hits the target IRR, the ratio flips (e.g., 5 to 95) to favor the non-tax (cash equity) investor. This Partnership Flip model is illustrative of the potential economics, but does not address the detailed Basis tracking account or partnership tracking accounts, each of which can have a significant impact on the actual allocations and returns.
E50: Customer Analysis
... E54: TRACK CHANGE DATES, AND CHANGES HERE:

Sheet Dashboard
H2: PROPRIETARY AND CONFIDENTIAL
H3: Demo Solar PV Model v2.1 | P3: Cautionary Note
H4: Dashboard | P4: This model is provided for illustration purposes only. Before using to evaluate any project, it should be audited to ensure functionality and accuracy, and to adapt the model to meet the specific requirements of applicable political and utility authorities, as well as any prospective customer, developer, EPC Contractor, investor, purchaser or lender. This model should not be used as tax advice. You should consult an accounting professional to determine if your specific circumstances allow you to be eligible for all of the credits/benefits demonstrated.
L5: Copyright, 2012, 2016, & 2020; All rights reserved by CapIron, Inc. This model may not be sold, licensed or distributed without the prior written approval of CapIron, Inc. DOE Solar District Cup Competitors may use this model for the competition and personal use only.
H6: DATA KEY | J6: Drop Down
J7: Input Variable
J8: Calculated
H10: Last Change
B11: 9 | H11: Last Change Date
B13: INPUTS AND CONSTANTS | N13: OUTPUTS AND ANALYSIS
N14: UNSTRUCTURED PROJECT
B16: SYSTEM INPUTS | G16: FINANCING INFORMATION - Construction | J16: INCOME & EXPENSE PROJECTIONS | N16: VALUE TO BUILDING/LANDLORD
D17: DC (W) | E17: AC (W) | G17: Construction Loan? | H17: No | J17: PPA Price per kWh (AC) | K17: 0.07303158 | N17: NPV Lease Payments | P17: =Unstructured!D149 -> 0
B18: Construction Cost/Watt | D18: =(1.42+0.012133)-D21 -> 1.2889197 | E18: =$D$18*$E$30 -> 1.5467036 | G18: Construction Loan Term (months) | H18: 3 | J18: PPA Price Annual Escalator | K18: 0.025 | N18: Roofing Upgrade & Warranty | P18: =Roof_Upgrade_Cost -> 0
B19: Roof Upgrade & Warranty | D19: 0 | E19: =$D$19*$E$30 -> 0 | G19: Construction Loan Amount | H19: 60855.612 | J19: SRECS | N19: Total NPV Value to Building/Landlord | P19: =SUM(P17:P18) -> 0
B20: Interconnection Costs | D20: 0 | E20: =$D$20*$E$30 -> 0 | G20: Construction Loan Rate | H20: 0.035 | J20: SRECS Applicable? | K20: No
B21: Developer Margin | D21: =(1.42+0.012133)*0.1 -> 0.1432133 | E21: =$D$21*$E$30 -> 0.17185596 | G21: Construction Loan Fee & Closing Cost | H21: 100000 | J21: SREC Price ($) | K21: 110 | N21: UNSTRUCTURED PROJECT ECONOMICS
B22: Total cost per watt | D22: =SUM(D18:D21) -> 1.432133 | E22: =SUM(E18:E21) -> 1.7185596 | G22: FINANCING INFORMATION - Tax Equity & Lease | J22: Single SREC Size (kWh/SREC) | K22: 1000 | N22: Investment | P22: =$H$23 -> 114975.09
B23: Size of System in W | D23: 77200 | E23: =Size_of_System_in_W_DC/$E$30 -> 64333.333 | G23: Project Sale Price | H23: =Aggregate_Project_Cost -> 114975.09 | J23: SREC Annual Rate Increase (Decrease) | K23: -0.025 | N23: Debt Portion | P23: =IF($H$27="Yes",$P$22*$H$32,0) -> 0
B24: Panel and Hard Eq. Cost per W | D24: 0 | E24: =$D$24*$E$30 -> 0 | G24: Equity Investment | H24: =Project_Sale_Price-IF(Project_Debt?="Yes",$H$30,0) -> 114975.09 | J24: SREC Term (Yrs) | K24: 10 | N24: Equity Portion | P24: =P22-P23 -> 114975.09
B25: Est. P50 Annual Production (kWh per kW DC) | E25: 1192.9807 | G25: Equity/Lessor Investor Discount Rate | H25: 0.065 | J25: Property & Equipment Taxes | N25: Project NPV @ Investor Hurdle | P25: =Unstructured!C89 -> -10574.11
B26: Annual Panel Degradation Rate | E26: 0.005 | F26: Sensitivity | G26: FINANCING INFORMATION - Project Debt | H26: ` | J26: Annual Site Property Tax Rate | K26: 0 | N26: Project IRR | P26: =Unstructured!C90 -> 0.051457314
B27: Est. Delta, P95/P50 | E27: 0.96 | F27: 1 | G27: Project Debt? | H27: No | J27: Initial Site Property Base Value | K27: =K34 -> 250000 | N27: Cash-on-Cash IRR | P27: =Unstructured!C83 -> 0.0147451
B28: Est. P50 kWh/year Production | E28: =(Size_of_System_in_W_DC/1000)*$E$25 -> 92098.11 | G28: Project Loan Term? | H28: 20 | J28: Site Property Annual Adjustment Rate | K28: 0.025
B29: Est. P95 kWh/year Production | E29: =$E$28*$E$27 -> 88414.186 | G29: Project Loan Rate | H29: 0.055 | J29: Annual Equipment Tax Rate | K29: 0 | N29: UNSTRUCTURED PROJECT ANALYSIS
B30: AC to DC Conversion Factor | E30: 1.2 | G30: Project Loan Amount | H30: 45990.036 | J30: Pers.Prop. Eq. Tax Base | K30: =Size_of_System_in_W_DC*$D$24 -> 0 | N30: Cash Flow Positive over Project Term? | P30: =Unstructured!$C$84 -> Pass
B31: SYSTEM COSTS | G31: Project Loan Coverage Ratio | H31: 1.25 | J31: Pers.Prop. Eq. Book Depr. Rate | K31: 0.05 | N31: Debt Amortize over Debt Term? | P31: =Unstructured!C106 -> N/A
B32: Aggregate Constr. Cost | E32: =Size_of_System_in_W_DC*$D$18 -> 99504.601 | G32: Project Debt/Project Debt+Equity | H32: =IF(H27="Yes",(H30/(H30+H24)),"N/A") -> N/A | J32: Site Costs | N32: Debt Coverage Ratio? | P32: =Unstructured!C105 -> N/A
B33: Aggregate Roof Upgrade & Warranty | E33: =$D$19*Size_of_System_in_W_DC -> 0 | G33: TAX DETAILS - Federal | J33: Site Purchase or Lease? | K33: Lease
B34: Interconnection Costs | E34: =$D$20*Size_of_System_in_W_DC -> 0 | G34: Owner is a Taxpayer or Non-Taxpayer | H34: Taxpayer | J34: Site Value or Purchase Price | K34: 250000 | N34: Construction Cost Recovery | P34: =E32 -> 99504.601
B35: Aggregate Developer Margin | E35: =$D$21*Size_of_System_in_W_DC -> 11056.067 | G35: Tax Efficient? | H35: State & Federal | J35: Site Lease Fixed or % of Revenue? | K35: Fixed | N35: Roof Upgrade Cost Recovery | P35: =E33 -> 0
B36: Site Purchase Price | E36: =IF(Site_Purchase_or_Lease?="Purchase",$K$34,0) -> 0 | G36: Depreciation Method | H36: MACRS | J36: Site Lease Include Site Lease Taxes? | K36: No | N36: Development Margin Recovery | P36: =E35 -> 11056.067
B37: Construction Loan Cost (IDC, Fees & Closing Cost) | E37: =IF(Construction_Loan?="Yes",Construction_Loan_Fee+(Construction_Loan_Amount*(Construction_Loan_Rate/12)*Construction_Loan_Term),0) -> 0 | G37: Depreciation Bonus Rate | H37: 0.5 | J37: Annual Site Lease Pmts (% of Rev.) | K37: 0.015 | N37: Other Cost Recovery | P37: =SUM(E36:E38) -> 4414.4224
B38: Closing Costs and Fees | E38: 4414.4224 | G38: Taxpayer's Federal Marginal Tax Rate | H38: 0.21 | J38: Annual Site Lease Fixed Cost | K38: 0 | N38: Excess Sale Price/Margin | P38: =$H$23-$E$39 -> 0
B39: Aggregate Project Cost | E39: =SUM(E32:E38) -> 114975.09 | G39: Use Federal ITC or PTC? | H39: ITC | J39: Annual Site Lease Escalator | K39: 0.025 | N39: Project Sale Price | P39: =SUM(P34:P38) -> 114975.09
G40: Federal ITC - Cash Sale -> On or Off? | H40: Off | J40: Other Operating Expenses
B41: CUSTOMER CONVENTIONAL POWER | G41: Federal Investment Tax Credit (ITC) | H41: =SUMIF($E$65:$E$68,"Yes",$D$65:$D$68) -> 0.3 | J41: Annual Ops & Maint. Costs per W (DC) | K41: =15.21/1000 -> 0.01521 | N41: Excess Investor IRR? | P41: =P26-H25 -> -0.013542686
B42: Utility Charge per kWh | E42: 0.073648296 | G42: ITC Cash Sale - Disc. to Purch. Price | H42: 0 | J42: Annual O&M Escalator | K42: 0.02
B43: Demand Charge Rate (% of Utility $/kWh) | E43: 0 | G43: ITC Cash Sale - # of Annual Pmts. | H43: 2 | J43: Insurance Expense per Year per W (DC) | K43: =3.85/1000 -> 0.00385
B44: Estimated Utility Charge Escalation | E44: 0.025 | G44: ITC Cash Sale - First Year Payment | H44: 1 | J44: Insurance Escalator | K44: 0.02 | N44: OUTPUTS AND ANALYSIS
B45: kWh Consumption (Avg. Monthly) | E45: 329401.92 | G45: PTC Term (years) | H45: 10 | N45: PARTNERSHIP FLIP | U45:  | X45: Customer Analysis
B46: Customer (NPV) Discount Rate | E46: 0.06 | G46: PTC Starting Rate ($/MWh) | H46: 26 | R46: =IF(Project_Debt?="Yes", "Partnership data compromised. Debt should be turned off in cell H27.","")
B47: Terminal Value (% of Purchase Price) for Buyout Calcs. | E47: 0.2 | G47: PTC Annual Inflator Rate (%) | H47: 0.02
G48: Add'l Reduction of ITC Eligible Basis | H48: 0.05 | N48: Partnership Flip Investment & Returns | X48: Customer Purchasing & Savings
B49: MACRS DEPRECIATION INFORMATION & TABLE | G49: Fed. ITC Eligible Property Value | H49: =(1-Additional_ITC_Basis_Reducer_Fine_Tuning)*(Project_Sale_Price-(Site_Purchase_Price+Roof_Upgrade_Cost+Other_Closing_Costs_Fees+IF($E$23>5000000,Interconnection_Costs,0))) -> 105032.63 | O49: Cash Equity | P49: Tax Equity | AA49: Annual
G50: Fed. ITC Dollar Value | H50: =H49*Federal_ITC_Rate*IF(AND(Owner_is_Taxpayer_Non_Taxpayer?="Non-Taxpayer", Project_Debt?="Yes"),1-MIN(0.15,Project_Loan_Amount/Project_Sale_Price),1) -> 31509.79 | N50: Equity Investment | O50: ='Partnership Flip'!C69 -> -63190.309 | P50: ='Partnership Flip'!C56 -> -51784.781 | X50: Customer Pricing | Y50: Year 1 | Z50: Year 20 | AA50: Esc. Rate
B51: Basis for Depreciation | E51: =(1-(0.5*Federal_ITC_Rate))*(Project_Sale_Price-(Site_Purchase_Price+Roof_Upgrade_Cost+Interconnection_Costs+Other_Closing_Costs_Fees))*(1-Additional_ITC_Basis_Reducer_Fine_Tuning) -> 89277.739 | G51: TAX DETAILS - State | N51: Equity Return | O51: ='Partnership Flip'!C75 -> 0.049390537 | P51: ='Partnership Flip'!C62 -> 0.065573809 | X51: Utility Price, $/kWh + Dem.Charge | Y51: ='Customer Analysis'!$D$22+'Customer Analysis'!$D$23 -> 0.073648296 | Z51: ='Customer Analysis'!$W$22+'Customer Analysis'!$W$23 -> 0.11773786 | AA51: =E44 -> 0.025
G52: Taxpayers State Income Tax Rate | H52: 0.025 | N52: Equity NPV | O52: ='Partnership Flip'!C74 -> -10635.056 | P52: ='Partnership Flip'!C61 -> 60.946624 | X52: PPA Price | Y52: ='Customer Analysis'!$D$24 -> 0.07303158 | Z52: ='Customer Analysis'!$W$24 -> 0.11675195 | AA52: =K18 -> 0.025
B53: Year | C53: MACRS* | D53: Federal | E53: State | G53: State ITC On or Off? | H53: On | N53: Cash-on-Cash Return | O53: ='Partnership Flip'!C77 -> 0.048850122 | P53: ='Partnership Flip'!C64 -> -0.092670539 | AA53: Annual
B54: 1 | C54: 0.2 | D54: =IF(Depreciation_Methodology?="MACRS",Depreciation_Basis*C54,IF(Depreciation_Methodology?="Bonus Depr.",((Depreciation_Basis*Depreciation_Bonus_Rate)+(Depreciation_Basis*((1-Depreciation_Bonus_Rate)*C54))),"ERROR")) -> 17855.548 | E54: =Depreciation_Basis*C54 -> 17855.548 | G54: State Tax Credit Rate | H54: 0 | X54: Electricity Purchases, kWh | Y54: Year 1 | Z54: Year 20 | AA54: Esc. Rate
B55: 2 | C55: 0.32 | D55: =IF(Depreciation_Methodology?="MACRS",Depreciation_Basis*C55,IF(Depreciation_Methodology?="Bonus Depr.",((Depreciation_Basis*((1-Depreciation_Bonus_Rate)*C55))),"ERROR")) -> 28568.877 | E55: =Depreciation_Basis*C55 -> 28568.877 | G55: State Tax Credit Basis | H55: =Depreciation_Basis -> 89277.739 | N55: Flip Year | P55: ='Partnership Flip'!C65 -> 6 | X55: Utility Purchases | Y55: ='Customer Analysis'!$D$19 -> 3860724.9 | Z55: ='Customer Analysis'!$W$19 -> 3869091.5 | AA55: =E26 -> 0.005
B56: 3 | C56: 0.192 | D56: =IF(Depreciation_Methodology?="MACRS",Depreciation_Basis*C56,IF(Depreciation_Methodology?="Bonus Depr.",((Depreciation_Basis*((1-Depreciation_Bonus_Rate)*C56))),"ERROR")) -> 17141.326 | E56: =Depreciation_Basis*C56 -> 17141.326 | G56: State Sales Tax on Electricity | H56: 0.07 | N56: Investment Ratio | P56: =(100*Dashboard!$H$62) &"% to " &(100*Dashboard!$H$63)&"% Ratio" -> 45.04% to 54.96% Ratio | X56: Solar Purchases | Y56: ='Customer Analysis'!$D$21 -> 92098.11 | Z56: ='Customer Analysis'!$W$21 -> 83731.573 | AA56: =-AA55 -> -0.005
B57: 4 | C57: 0.1152 | D57: =IF(Depreciation_Methodology?="MACRS",Depreciation_Basis*C57,IF(Depreciation_Methodology?="Bonus Depr.",((Depreciation_Basis*((1-Depreciation_Bonus_Rate)*C57))),"ERROR")) -> 10284.796 | E57: =Depreciation_Basis*C57 -> 10284.796 | G57: Partnership Flip Data
B58: 5 | C58: 0.1152 | D58: =IF(Depreciation_Methodology?="MACRS",Depreciation_Basis*C58,IF(Depreciation_Methodology?="Bonus Depr.",((Depreciation_Basis*((1-Depreciation_Bonus_Rate)*C58))),"ERROR")) -> 10284.796 | E58: =Depreciation_Basis*C58 -> 10284.796 | G58: Tax Equity Partner, Pre-Flip Share | H58: 0.99 | N58: Project Flip Project Analysis | X58: Customer Buyout and Lifecycle Analysis
B59: 6 | C59: 0.0576 | D59: =IF(Depreciation_Methodology?="MACRS",Depreciation_Basis*C59,IF(Depreciation_Methodology?="Bonus Depr.",((Depreciation_Basis*((1-Depreciation_Bonus_Rate)*C59))),"ERROR")) -> 5142.3978 | E59: =Depreciation_Basis*C59 -> 5142.3978 | G59: Cash Equity Partner, Pre-Flip Share | H59: =1-$H$58 -> 0.01 | N59: Cash Flow Positive over Project Term? | P59: =Unstructured!$C$84 -> Pass | Y59: Year 1 | Z59: Year 7 | AA59: Year 15
C60: (5yrs, MACRS, HY) | D60: =SUM(D54:D59) -> 89277.739 | E60: =SUM(E54:E59) -> 89277.739 | G60: Tax Equity Partner, Post-Flip Share | H60: 0.05 | N60: Debt Amortize over Debt Term? | P60: N/A | X60: Est. FMV Customer Buyout | Y60: =Dashboard!H23 -> 114975.09 | Z60: ='Customer Analysis'!$J$34 -> 58787.204 | AA60: ='Customer Analysis'!$M$34 -> 56298.414
G61: Cash Equity Partner, Post-Flip Share | H61: =1-$H$60 -> 0.95 | N61: Debt Coverage Ratio? | P61: N/A
G62: Tax Equity, % of Equity Investment | H62: 0.4504 | X62: Est. Lifecycle Benefit (Cost) | Y62: ='Customer Analysis'!$C$56 -> 0.063471683 | Z62: ='Customer Analysis'!$C$57 -> 0.059869119 | AA62: ='Customer Analysis'!$C$58 -> 0.06894082
B63: ITC AND ITC ADDER TABLE | G63: Cash Equity, % of Equity Investment | H63: =1-Tax_Equity_Investment_Share -> 0.5496 | N63: Construction Cost Recovery | P63: =E32 -> 99504.601
B64: Type | D64: Rate | E64: Eligible? | G64: Time-Based Flip, Target Year (>=5) | H64: 5 | N64: Roof Upgrade Cost Recovery | P64: =Roof_Upgrade_Cost -> 0 | X64: Customer System Upfront Purchase
B65: Base Rate for ITC | D65: 0.3 | E65: Yes | G65: Investor Target Flip IRR | H65: =Investor_Discount_Rate -> 0.065 | N65: Development Margin Recovery | P65: =E35 -> 11056.067 | X65: Purchase Price | Z65: =Y60 -> 114975.09
B66: Domestic Content | D66: 0.1 | E66: No | G66: Cash-On-Cash Premium Requirement | H66: 0.035 | N66: Other Cost Recovery | P66: =SUM(E36:E38) -> 4414.4224 | X66: NPV | Z66: ='Customer Analysis'!$C$70 -> -6535.8369
B67: Energy Community | D67: 0.1 | E67: No | G67: Mgt. Fee, % of Remaining Cash Flow | H67: 0.9 | N67: Excess Sale Price/Margin | P67: =$H$23-$E$39 -> 0 | X67: IRR | Z67: ='Customer Analysis'!$C$71 -> 0.080229392
B68: Low-Income Allocation | D68: 0.1 | E68: No | N68: Project Sale Price | P68: =SUM(P63:P67) -> 114975.09
B70: Termination Value - % of Aggregate Project Cost Taken as a Sale @Term End (For IRR & NPV Calcs | N70: Excess Investor IRR? | P70: =P51-H25 -> 0.00057380851
B72: Term Value - % | C72: 0.12 | D72: 0.15 | E72: 0.18
B73: Term. Value - $ | C73: =Aggregate_Project_Cost*C72 -> 13797.011 | D73: =Aggregate_Project_Cost*D72 -> 17246.264 | E73: =Aggregate_Project_Cost*E72 -> 20695.516
B74: Selector for Model Returns: | D74: On | E74: 0.15
B80: OUTPUTS: Automated summary of critical assumptions. Review with each iteration of the model.
B81: ---> | C81: ="Solar System size is set to "&TEXT(Size_of_System_in_W_DC,"0,0")&" W(dc), with an AC/DC Conversion Ratio of "&TEXT($E$30*100,0)&"%." -> Solar System size is set to 77,200 W(dc), with an AC/DC Conversion Ratio of 120%.
B82: ---> | C82: ="Solar Production is based upon a manual entry of "&TEXT(Manual_Entry_Estimated_P50_Production,"0,0")&" kWhs per kW(dc)." -> Solar Production is based upon a manual entry of 1,193 kWhs per kW(dc).
B83: ---> | C83: ="P50 Solar Production for the 1st Year is estimated to be "&TEXT(P50_Production_1st_Yr,"#,#")&" kWhs." -> P50 Solar Production for the 1st Year is estimated to be 92,098 kWhs.
B84: ---> | C84: ="Federal ITC is set for "&TEXT(100*Federal_ITC_Rate,0)&"%." -> Federal ITC is set for 30%.
B85: ---> | C85: ="Development Margins are set to $"&TEXT(D21,"0.00")&" per W(dc), for a total Development Margin of $"&TEXT(ROUNDUP(E35,0),"0,0")&"." -> Development Margins are set to $0.14 per W(dc), for a total Development Margin of $11,057.
B86: ---> | C86: ="Constsruction Costs are set to $"&TEXT(D18,"0.00")&" per W(dc), for a total build cost of $"&TEXT(ROUNDUP(Aggregate_Construction_Cost,0),"0,0")&", excluding Interconnection Costs and Development Costs." -> Constsruction Costs are set to $1.29 per W(dc), for a total build cost of $99,505, excluding Interconnection Costs and Development Costs.
B87: ---> | C87: ="Interconnection Costs are set to $"&TEXT(D20,"0.00")&" per Watt(dc) for a total Interconnection cost of $"&TEXT(ROUNDUP(Interconnection_Costs,0),"0,0")&" (all non-ITC/MACRS eligible)." -> Interconnection Costs are set to $0.00 per Watt(dc) for a total Interconnection cost of $00 (all non-ITC/MACRS eligible).
B88: ---> | C88: ="Rooftop Upgrade & Warranty Costs are set to $"&TEXT(D19,"0.00")&" per Watt(dc) for a total Rooftop Upgrade & Warranty Cost of $"&TEXT(ROUNDUP(Roof_Upgrade_Cost,0),"0,0.00")&" (all non-ITC/MACRS eligible)." -> Rooftop Upgrade & Warranty Costs are set to $0.00 per Watt(dc) for a total Rooftop Upgrade & Warranty Cost of $00.00 (all non-ITC/MACRS eligible).
B89: ---> | C89: =IF(Construction_Loan?="Yes", "Construction Loan is on, with a borrowing term of "&TEXT(Construction_Loan_Term,0)&" months, a loan amount of $"&TEXT(Construction_Loan_Amount,"0,0")&" at an interest rate of "&TEXT(Construction_Loan_Rate*100,0)&" % interest per year. Fees and closing costs are $"&TEXT(Construction_Loan_Fee,"0,0.00")&".", "There is no Consturction Loan.") -> There is no Consturction Loan.
B90: ---> | C90: ="PPA Term is set for 25 years, with a starting rate of $"&TEXT(PPA_Price_kWh,"0.00")&" per kWh, escalating at an annual rate of "&TEXT(PPA_Price_Annual_Escalator*100,"0.00")&"%." -> PPA Term is set for 25 years, with a starting rate of $0.07 per kWh, escalating at an annual rate of 2.50%.
B91: ---> | C91: =IF(SRECs_Applicable?="Yes", "SRECS are included, and priced at $"&TEXT(SREC_Price,"0.00")&" per SREC, with a "&TEXT(100*SREC_Increase_Decrease,"0.00")&"% annual escalator over a "&TEXT(SREC_Term_Yrs,0)&" year term.","No SRECS applicable.") -> No SRECS applicable.
B92: ---> | C92: =IF(Project_Debt?="Yes", "Project is leveraged with a loan amount of $"&TEXT(Project_Loan_Amount,"0,0")&" at "&TEXT(100*Project_Loan_Rate,"0.00")&"% requiring a Loan Payment Coverage Ratio of "&TEXT(Project_Loan_Coverage_Ratio*100,"0.00")&"% over a term of "&TEXT(Project_Loan_Term?,"0")&" years.","No debt leverage.") -> No debt leverage.
B93: ---> | C93: ="Project Cash Flow "&IF(AND(Project_Debt?="Yes",P30="Pass"),"remains positive over the full Debt Term. ","does NOT remain positive over the full Debt Term. ")&IF(P31="Yes","The loan fully amortizes over the debt term, and ","The loan FAILS to fully amortize over the debt term, and ")&IF(P32="Pass","the cash flows are sufficient to support the Debt Coverage Ratio.","the cash flows are NOT sufficient to support the Debt Coverage Ratio.") -> Project Cash Flow does NOT remain positive over the full Debt Term. The loan FAILS to fully amortize over the debt term, and the cash flows are NOT sufficient to support the Debt Coverage Ratio.
B94: ---> | C94: =IF(Owner_is_Taxpayer_Non_Taxpayer?="Non-Taxpayer","Owner is treated as a Non-Taxpayer. ","Owner is treated as a Taxpayer. Taxpayer's tax efficiency setting is "&TEXT(Tax_Efficient_Status?,0)&", and Depreciation methodology is set for "&TEXT(Depreciation_Methodology?,"")&".") -> Owner is treated as a Taxpayer. Taxpayer's tax efficiency setting is State & Federal, and Depreciation methodology is set for MACRS.
B95: ---> | C95: =IF(Tax_Credit_Selector_ITC_or_PTC="PTC","Tax Credit selected is PTC with a term of "&TEXT(PTC_Term_in_Years,0)&" years, a starting PTC price of $"&TEXT(PTC_Starting_Rate_Dollars_per_MWh,0)&" per MWh.",IF(AND(Tax_Credit_Selector_ITC_or_PTC="ITC",Federal_ITC_Cash_Sale_OnOff="On"),"Tax Credit is set for ITC. The ITC Cash Sale is On, with a discount to the sale price of "&TEXT(ITC_Cash_Sale_Discount_to_Purchase_Price*100,0)&"%, payable in "&TEXT(ITC_Cash_Sale_Number_of_Annual_Payments,0)&" annual payment(s) beginning in model year "&TEXT(ITC_Cash_Sale_First_Year_Payment,0)&".","Tax Credit selected is ITC with NO cash sale.")) -> Tax Credit selected is ITC with NO cash sale.
B96: ---> | C96: =IF(Tax_Credit_Selector_ITC_or_PTC="ITC","The calculated value of the ITC is "&TEXT(Federal_ITC_Rate*100,0)&"%. Be sure to check active and inactive Adders for accuracy.","Not Applicable") -> The calculated value of the ITC is 30%. Be sure to check active and inactive Adders for accuracy.
B97: ---> | C97: =IF(Termination_Value_OnOff="On","The model assumes a termination value at the end of the 25-year term, equal to "&TEXT(Termination_Value_Percentage*100,0)&"% of the original Project Sale Price of $"&TEXT(Project_Sale_Price,"0,0")&". That termination value is $"&TEXT(Termination_Value_Percentage*Project_Sale_Price,"0,0")&".", "There is no termination value in this model iteration.") -> The model assumes a termination value at the end of the 25-year term, equal to 15% of the original Project Sale Price of $114,975. That termination value is $17,246.
J138: Demo Solar PV Model v2.1 | M138: PROPRIETARY AND CONFIDENTIAL
J139: Dashboard
N140: Copyright, 2012, 2016, & 2020; All rights reserved by CapIron, Inc. This model may not be sold, licensed or distributed without the prior written approval of CapIron, Inc. Solar District Cup students may use this model for their competition use only.
J141: DATA KEY | K141: Drop Down
K142: Input Variable
K143: Calculated
J145: Last Change
J146: Last Change Date

Sheet Unstructured
H2: PROPRIETARY AND CONFIDENTIAL
H4: Demo Solar PV Model v.2.1 | O4: Cautionary Note
H5: Unstructured Model | O5: This model is provided for illustration purposes only. Before using to evaluate any project, it should be audited to ensure functionality and accuracy, and to adapt the model to meet the specific requirements of applicable political and utility authorities, as well as any prospective customer, developer, EPC Contractor, investor, purchaser or lender. This model should not be used as tax advice. You should consult an accounting professional to determine if your specific circumstances allow you to be eligible for all of the credits/benefits demonstrated.
H7: Copyright, 2012 & 2013; All rights reserved by CapIron, Inc. This model may not be sold, licensed or distributed without the prior written approval of CapIron, Inc. Heatspring Solar MBA students may use this model for their personal use only.
H10: Last Change
H11: Last Change Date
B13: SUPPORTING DATA AND CALCULATIONS
B14: Unstructured Project
B16: Unstructured Project Economics
B17: Year | C17: 0 | D17: =C17+1 -> 1 | E17: =D17+1 -> 2 | F17: =E17+1 -> 3 | G17: =F17+1 -> 4 | H17: =G17+1 -> 5 | I17: =H17+1 -> 6 | J17: =I17+1 -> 7 | K17: =J17+1 -> 8 | ... AB17: =AA17+1 -> 25
B18: Project Revenue Data
B19: PPA Price per kWh | D19: =PPA_Price_kWh -> 0.07303158 | E19: =D19*(1+PPA_Price_Annual_Escalator) -> 0.07485737 | F19: =E19*(1+PPA_Price_Annual_Escalator) -> 0.076728804 | G19: =F19*(1+PPA_Price_Annual_Escalator) -> 0.078647024 | H19: =G19*(1+PPA_Price_Annual_Escalator) -> 0.0806132 | I19: =H19*(1+PPA_Price_Annual_Escalator) -> 0.08262853 | J19: =I19*(1+PPA_Price_Annual_Escalator) -> 0.084694243 | K19: =J19*(1+PPA_Price_Annual_Escalator) -> 0.086811599 | L19: =K19*(1+PPA_Price_Annual_Escalator) -> 0.088981889 | ... AB19: =AA19*(1+PPA_Price_Annual_Escalator) -> 0.13209411
B20: SREC Price | D20: =IF(AND(SRECs_Applicable?="Yes",D17<=SREC_Term_Yrs),SREC_Price,0) -> 0 | E20: =IF(AND(SRECs_Applicable?="Yes",E17<=SREC_Term_Yrs),D20,0)*(1+SREC_Increase_Decrease) -> 0 | F20: =IF(AND(SRECs_Applicable?="Yes",F17<=SREC_Term_Yrs),E20,0)*(1+SREC_Increase_Decrease) -> 0 | G20: =IF(AND(SRECs_Applicable?="Yes",G17<=SREC_Term_Yrs),F20,0)*(1+SREC_Increase_Decrease) -> 0 | H20: =IF(AND(SRECs_Applicable?="Yes",H17<=SREC_Term_Yrs),G20,0)*(1+SREC_Increase_Decrease) -> 0 | I20: =IF(AND(SRECs_Applicable?="Yes",I17<=SREC_Term_Yrs),H20,0)*(1+SREC_Increase_Decrease) -> 0 | J20: =IF(AND(SRECs_Applicable?="Yes",J17<=SREC_Term_Yrs),I20,0)*(1+SREC_Increase_Decrease) -> 0 | K20: =IF(AND(SRECs_Applicable?="Yes",K17<=SREC_Term_Yrs),J20,0)*(1+SREC_Increase_Decrease) -> 0 | L20: =IF(AND(SRECs_Applicable?="Yes",L17<=SREC_Term_Yrs),K20,0)*(1+SREC_Increase_Decrease) -> 0 | ... AB20: =IF(AND(SRECs_Applicable?="Yes",AB17<=SREC_Term_Yrs),AA20,0)*(1+SREC_Increase_Decrease) -> 0
B21: P50 Production (kWh) | D21: =P50_Production_1st_Yr -> 92098.11 | E21: =D21*(1-Panel_Degradation_Rate) -> 91637.619 | F21: =E21*(1-Panel_Degradation_Rate) -> 91179.431 | G21: =F21*(1-Panel_Degradation_Rate) -> 90723.534 | H21: =G21*(1-Panel_Degradation_Rate) -> 90269.917 | I21: =H21*(1-Panel_Degradation_Rate) -> 89818.567 | J21: =I21*(1-Panel_Degradation_Rate) -> 89369.474 | K21: =J21*(1-Panel_Degradation_Rate) -> 88922.627 | L21: =K21*(1-Panel_Degradation_Rate) -> 88478.014 | ... AB21: =AA21*(1-Panel_Degradation_Rate) -> 81659.113
B22: PTC Price ($/MWh) | D22: =PTC_Starting_Rate_Dollars_per_MWh -> 26 | E22: =IF(E17<=PTC_Term_in_Years,D22*(1+PTC_Annual_Inflator_Rate_Percent),0) -> 26.52 | F22: =IF(F17<=PTC_Term_in_Years,E22*(1+PTC_Annual_Inflator_Rate_Percent),0) -> 27.0504 | G22: =IF(G17<=PTC_Term_in_Years,F22*(1+PTC_Annual_Inflator_Rate_Percent),0) -> 27.591408 | H22: =IF(H17<=PTC_Term_in_Years,G22*(1+PTC_Annual_Inflator_Rate_Percent),0) -> 28.143236 | I22: =IF(I17<=PTC_Term_in_Years,H22*(1+PTC_Annual_Inflator_Rate_Percent),0) -> 28.706101 | J22: =IF(J17<=PTC_Term_in_Years,I22*(1+PTC_Annual_Inflator_Rate_Percent),0) -> 29.280223 | K22: =IF(K17<=PTC_Term_in_Years,J22*(1+PTC_Annual_Inflator_Rate_Percent),0) -> 29.865827 | L22: =IF(L17<=PTC_Term_in_Years,K22*(1+PTC_Annual_Inflator_Rate_Percent),0) -> 30.463144 | ... AB22: =IF(AB17<=PTC_Term_in_Years,AA22*(1+PTC_Annual_Inflator_Rate_Percent),0) -> 0
B23: P50 SRECs | D23: =IF(D17<=SREC_Term_Yrs,D21/SREC_Size_kWh_per_SREC,0) -> 92.09811 | E23: =IF(E17<=SREC_Term_Yrs,E21/SREC_Size_kWh_per_SREC,0) -> 91.637619 | F23: =IF(F17<=SREC_Term_Yrs,F21/SREC_Size_kWh_per_SREC,0) -> 91.179431 | G23: =IF(G17<=SREC_Term_Yrs,G21/SREC_Size_kWh_per_SREC,0) -> 90.723534 | H23: =IF(H17<=SREC_Term_Yrs,H21/SREC_Size_kWh_per_SREC,0) -> 90.269917 | I23: =IF(I17<=SREC_Term_Yrs,I21/SREC_Size_kWh_per_SREC,0) -> 89.818567 | J23: =IF(J17<=SREC_Term_Yrs,J21/SREC_Size_kWh_per_SREC,0) -> 89.369474 | K23: =IF(K17<=SREC_Term_Yrs,K21/SREC_Size_kWh_per_SREC,0) -> 88.922627 | ... AB23: =IF(AB17<=SREC_Term_Yrs,AB21/SREC_Size_kWh_per_SREC,0) -> 0
B25: Project Revenue
B26: P50 Revenue - Production | D26: =D21*D19 -> 6726.0705 | E26: =E21*E19 -> 6859.7512 | F26: =F21*F19 -> 6996.0887 | G26: =G21*G19 -> 7135.136 | H26: =H21*H19 -> 7276.9468 | I26: =I21*I19 -> 7421.5761 | J26: =J21*J19 -> 7569.0799 | K26: =K21*K19 -> 7719.5154 | ... AB26: =AB21*AB19 -> 10786.688
B27: P50 Revenue - SREC | D27: =D23*D20 -> 0 | E27: =E23*E20 -> 0 | F27: =F23*F20 -> 0 | G27: =G23*G20 -> 0 | H27: =H23*H20 -> 0 | I27: =I23*I20 -> 0 | J27: =J23*J20 -> 0 | K27: =K23*K20 -> 0 | ... AB27: =AB23*AB20 -> 0
B28: Gross Project Revenue | D28: =SUM(D26:D27) -> 6726.0705 | E28: =SUM(E26:E27) -> 6859.7512 | F28: =SUM(F26:F27) -> 6996.0887 | G28: =SUM(G26:G27) -> 7135.136 | H28: =SUM(H26:H27) -> 7276.9468 | I28: =SUM(I26:I27) -> 7421.5761 | J28: =SUM(J26:J27) -> 7569.0799 | K28: =SUM(K26:K27) -> 7719.5154 | ... AB28: =SUM(AB26:AB27) -> 10786.688
B29: Less Sales Tax | D29: =State_Sales_Tax*Unstructured!D28 -> 470.82494 | E29: =State_Sales_Tax*Unstructured!E28 -> 480.18258 | F29: =State_Sales_Tax*Unstructured!F28 -> 489.72621 | G29: =State_Sales_Tax*Unstructured!G28 -> 499.45952 | H29: =State_Sales_Tax*Unstructured!H28 -> 509.38628 | I29: =State_Sales_Tax*Unstructured!I28 -> 519.51033 | J29: =State_Sales_Tax*Unstructured!J28 -> 529.8356 | K29: =State_Sales_Tax*Unstructured!K28 -> 540.36608 | ... AB29: =State_Sales_Tax*Unstructured!AB28 -> 755.06817
B30: Total Project Revenue | D30: =SUM(D28-D29) -> 6255.2456 | E30: =SUM(E28-E29) -> 6379.5686 | F30: =SUM(F28-F29) -> 6506.3625 | G30: =SUM(G28-G29) -> 6635.6765 | H30: =SUM(H28-H29) -> 6767.5605 | I30: =SUM(I28-I29) -> 6902.0658 | J30: =SUM(J28-J29) -> 7039.2443 | K30: =SUM(K28-K29) -> 7179.1493 | ... AB30: =SUM(AB28-AB29) -> 10031.62
B32: Project Operating Costs
B33: O&M Costs | D33: =OandM_Cost_per_W_DC*Size_of_System_in_W_DC -> 1174.212 | E33: =Size_of_System_in_W_DC*(OandM_Cost_per_W_DC*((1+OandM_Cost_Escalator)^(E17-1))) -> 1197.6962 | F33: =Size_of_System_in_W_DC*(OandM_Cost_per_W_DC*((1+OandM_Cost_Escalator)^(F17-1))) -> 1221.6502 | G33: =Size_of_System_in_W_DC*(OandM_Cost_per_W_DC*((1+OandM_Cost_Escalator)^(G17-1))) -> 1246.0832 | H33: =Size_of_System_in_W_DC*(OandM_Cost_per_W_DC*((1+OandM_Cost_Escalator)^(H17-1))) -> 1271.0048 | I33: =Size_of_System_in_W_DC*(OandM_Cost_per_W_DC*((1+OandM_Cost_Escalator)^(I17-1))) -> 1296.4249 | J33: =Size_of_System_in_W_DC*(OandM_Cost_per_W_DC*((1+OandM_Cost_Escalator)^(J17-1))) -> 1322.3534 | K33: =Size_of_System_in_W_DC*(OandM_Cost_per_W_DC*((1+OandM_Cost_Escalator)^(K17-1))) -> 1348.8005 | L33: =Size_of_System_in_W_DC*(OandM_Cost_per_W_DC*((1+OandM_Cost_Escalator)^(L17-1))) -> 1375.7765 | ... AB33: =Size_of_System_in_W_DC*(OandM_Cost_per_W_DC*((1+OandM_Cost_Escalator)^(AB17-1))) -> 1888.6463
B34: Site Lease Costs | D34: =IF(AND(Site_Purchase_or_Lease?="Lease",Site_Lease_Fixed_or_PercentofRev="% of Revenue"),D30*Site_Lease_Percent_of_Revenue,IF(AND(Site_Purchase_or_Lease?="Lease",Site_Lease_Fixed_or_PercentofRev="Fixed"),Site_Lease_Fixed_Cost,0)) -> 0 | E34: =IF(AND(Site_Purchase_or_Lease?="Lease",Site_Lease_Fixed_or_PercentofRev="% of Revenue"),E30*Site_Lease_Percent_of_Revenue,IF(AND(Site_Purchase_or_Lease?="Lease",Site_Lease_Fixed_or_PercentofRev="Fixed"),Site_Lease_Fixed_Cost*((1+Site_Lease_Fixed_Escalator)^(E17-1)),0)) -> 0 | F34: =IF(AND(Site_Purchase_or_Lease?="Lease",Site_Lease_Fixed_or_PercentofRev="% of Revenue"),F30*Site_Lease_Percent_of_Revenue,IF(AND(Site_Purchase_or_Lease?="Lease",Site_Lease_Fixed_or_PercentofRev="Fixed"),Site_Lease_Fixed_Cost*((1+Site_Lease_Fixed_Escalator)^(F17-1)),0)) -> 0 | G34: =IF(AND(Site_Purchase_or_Lease?="Lease",Site_Lease_Fixed_or_PercentofRev="% of Revenue"),G30*Site_Lease_Percent_of_Revenue,IF(AND(Site_Purchase_or_Lease?="Lease",Site_Lease_Fixed_or_PercentofRev="Fixed"),Site_Lease_Fixed_Cost*((1+Site_Lease_Fixed_Escalator)^(G17-1)),0)) -> 0 | H34: =IF(AND(Site_Purchase_or_Lease?="Lease",Site_Lease_Fixed_or_PercentofRev="% of Revenue"),H30*Site_Lease_Percent_of_Revenue,IF(AND(Site_Purchase_or_Lease?="Lease",Site_Lease_Fixed_or_PercentofRev="Fixed"),Site_Lease_Fixed_Cost*((1+Site_Lease_Fixed_Escalator)^(H17-1)),0)) -> 0 | I34: =IF(AND(Site_Purchase_or_Lease?="Lease",Site_Lease_Fixed_or_PercentofRev="% of Revenue"),I30*Site_Lease_Percent_of_Revenue,IF(AND(Site_Purchase_or_Lease?="Lease",Site_Lease_Fixed_or_PercentofRev="Fixed"),Site_Lease_Fixed_Cost*((1+Site_Lease_Fixed_Escalator)^(I17-1)),0)) -> 0 | J34: =IF(AND(Site_Purchase_or_Lease?="Lease",Site_Lease_Fixed_or_PercentofRev="% of Revenue"),J30*Site_Lease_Percent_of_Revenue,IF(AND(Site_Purchase_or_Lease?="Lease",Site_Lease_Fixed_or_PercentofRev="Fixed"),Site_Lease_Fixed_Cost*((1+Site_Lease_Fixed_Escalator)^(J17-1)),0)) -> 0 | K34: =IF(AND(Site_Purchase_or_Lease?="Lease",Site_Lease_Fixed_or_PercentofRev="% of Revenue"),K30*Site_Lease_Percent_of_Revenue,IF(AND(Site_Purchase_or_Lease?="Lease",Site_Lease_Fixed_or_PercentofRev="Fixed"),Site_Lease_Fixed_Cost*((1+Site_Lease_Fixed_Escalator)^(K17-1)),0)) -> 0 | L34: =IF(AND(Site_Purchase_or_Lease?="Lease",Site_Lease_Fixed_or_PercentofRev="% of Revenue"),L30*Site_Lease_Percent_of_Revenue,IF(AND(Site_Purchase_or_Lease?="Lease",Site_Lease_Fixed_or_PercentofRev="Fixed"),Site_Lease_Fixed_Cost*((1+Site_Lease_Fixed_Escalator)^(L17-1)),0)) -> 0 | ... AB34: =IF(AND(Site_Purchase_or_Lease?="Lease",Site_Lease_Fixed_or_PercentofRev="% of Revenue"),AB30*Site_Lease_Percent_of_Revenue,IF(AND(Site_Purchase_or_Lease?="Lease",Site_Lease_Fixed_or_PercentofRev="Fixed"),Site_Lease_Fixed_Cost*((1+Site_Lease_Fixed_Escalator)^(AB17-1)),0)) -> 0
B35: Site Property Tax | D35: =IF(OR(Site_Purchase_or_Lease?="Purchase",AND(Site_Purchase_or_Lease?="Lease",Site_Lease_Includes_Taxes="No")),Property_Site_Base_Value*Property_Site_Tax_Rate,0) -> 0 | E35: =D35*(1+Property_Site_Value_Adj_Rate) -> 0 | F35: =E35*(1+Property_Site_Value_Adj_Rate) -> 0 | G35: =F35*(1+Property_Site_Value_Adj_Rate) -> 0 | H35: =G35*(1+Property_Site_Value_Adj_Rate) -> 0 | I35: =H35*(1+Property_Site_Value_Adj_Rate) -> 0 | J35: =I35*(1+Property_Site_Value_Adj_Rate) -> 0 | K35: =J35*(1+Property_Site_Value_Adj_Rate) -> 0 | L35: =K35*(1+Property_Site_Value_Adj_Rate) -> 0 | ... AB35: =AA35*(1+Property_Site_Value_Adj_Rate) -> 0
B36: Equipment Tax | D36: =Property_Equip_Tax_Rate*Property_Equip_Base_Value -> 0 | E36: =Property_Equip_Base_Value*((1-Property_Equip_Book_Adj_Rate)^(E17-1)*Property_Equip_Tax_Rate) -> 0 | F36: =Property_Equip_Base_Value*((1-Property_Equip_Book_Adj_Rate)^(F17-1)*Property_Equip_Tax_Rate) -> 0 | G36: =Property_Equip_Base_Value*((1-Property_Equip_Book_Adj_Rate)^(G17-1)*Property_Equip_Tax_Rate) -> 0 | H36: =Property_Equip_Base_Value*((1-Property_Equip_Book_Adj_Rate)^(H17-1)*Property_Equip_Tax_Rate) -> 0 | I36: =Property_Equip_Base_Value*((1-Property_Equip_Book_Adj_Rate)^(I17-1)*Property_Equip_Tax_Rate) -> 0 | J36: =Property_Equip_Base_Value*((1-Property_Equip_Book_Adj_Rate)^(J17-1)*Property_Equip_Tax_Rate) -> 0 | K36: =Property_Equip_Base_Value*((1-Property_Equip_Book_Adj_Rate)^(K17-1)*Property_Equip_Tax_Rate) -> 0 | L36: =Property_Equip_Base_Value*((1-Property_Equip_Book_Adj_Rate)^(L17-1)*Property_Equip_Tax_Rate) -> 0 | ... AB36: =Property_Equip_Base_Value*((1-Property_Equip_Book_Adj_Rate)^(AB17-1)*Property_Equip_Tax_Rate) -> 0
B37: Insurance | D37: =Insurance_Cost_per_Watt_DC*Size_of_System_in_W_DC -> 297.22 | E37: =Size_of_System_in_W_DC*((1+Insurance_Cost_Escalator)^(E17-1)*Insurance_Cost_per_Watt_DC) -> 303.1644 | F37: =Size_of_System_in_W_DC*((1+Insurance_Cost_Escalator)^(F17-1)*Insurance_Cost_per_Watt_DC) -> 309.22769 | G37: =Size_of_System_in_W_DC*((1+Insurance_Cost_Escalator)^(G17-1)*Insurance_Cost_per_Watt_DC) -> 315.41224 | H37: =Size_of_System_in_W_DC*((1+Insurance_Cost_Escalator)^(H17-1)*Insurance_Cost_per_Watt_DC) -> 321.72049 | I37: =Size_of_System_in_W_DC*((1+Insurance_Cost_Escalator)^(I17-1)*Insurance_Cost_per_Watt_DC) -> 328.1549 | J37: =Size_of_System_in_W_DC*((1+Insurance_Cost_Escalator)^(J17-1)*Insurance_Cost_per_Watt_DC) -> 334.71799 | K37: =Size_of_System_in_W_DC*((1+Insurance_Cost_Escalator)^(K17-1)*Insurance_Cost_per_Watt_DC) -> 341.41235 | L37: =Size_of_System_in_W_DC*((1+Insurance_Cost_Escalator)^(L17-1)*Insurance_Cost_per_Watt_DC) -> 348.2406 | ... AB37: =Size_of_System_in_W_DC*((1+Insurance_Cost_Escalator)^(AB17-1)*Insurance_Cost_per_Watt_DC) -> 478.05972
B38: Total Project Operating Costs | D38: =SUM(D33:D37) -> 1471.432 | E38: =SUM(E33:E37) -> 1500.8606 | F38: =SUM(F33:F37) -> 1530.8779 | G38: =SUM(G33:G37) -> 1561.4954 | H38: =SUM(H33:H37) -> 1592.7253 | I38: =SUM(I33:I37) -> 1624.5798 | J38: =SUM(J33:J37) -> 1657.0714 | K38: =SUM(K33:K37) -> 1690.2128 | ... AB38: =SUM(AB33:AB37) -> 2366.706
B40: EBITDA (Cash Flow) | D40: =D30-D38 -> 4783.8136 | E40: =E30-E38 -> 4878.7079 | F40: =F30-F38 -> 4975.4846 | G40: =G30-G38 -> 5074.181 | H40: =H30-H38 -> 5174.8352 | I40: =I30-I38 -> 5277.486 | J40: =J30-J38 -> 5382.1729 | K40: =K30-K38 -> 5488.9365 | ... AB40: =AB30-AB38 -> 7664.9139
B42: Interest Payments | D42: =IF(Project_Debt?="Yes",D99,0) -> 0 | E42: =IF(Project_Debt?="Yes",E99,0) -> 0 | F42: =IF(Project_Debt?="Yes",F99,0) -> 0 | G42: =IF(Project_Debt?="Yes",G99,0) -> 0 | H42: =IF(Project_Debt?="Yes",H99,0) -> 0 | I42: =IF(Project_Debt?="Yes",I99,0) -> 0 | J42: =IF(Project_Debt?="Yes",J99,0) -> 0 | K42: =IF(Project_Debt?="Yes",K99,0) -> 0 | ... AB42: =IF(Project_Debt?="Yes",AB99,0) -> 0
B44: Depreciation
B45: State | D45: =IF(OR(Tax_Efficient_Status?="Not Efficient",Tax_Efficient_Status?="Federal Only"),(Unstructured!D114+Unstructured!D115),D114) -> 17855.548 | E45: =IF(OR(Tax_Efficient_Status?="Not Efficient",Tax_Efficient_Status?="Federal Only"),(Unstructured!E114+Unstructured!E115),E114) -> 28568.877 | F45: =IF(OR(Tax_Efficient_Status?="Not Efficient",Tax_Efficient_Status?="Federal Only"),(Unstructured!F114+Unstructured!F115),F114) -> 17141.326 | G45: =IF(OR(Tax_Efficient_Status?="Not Efficient",Tax_Efficient_Status?="Federal Only"),(Unstructured!G114+Unstructured!G115),G114) -> 10284.796 | H45: =IF(OR(Tax_Efficient_Status?="Not Efficient",Tax_Efficient_Status?="Federal Only"),(Unstructured!H114+Unstructured!H115),H114) -> 10284.796 | I45: =IF(OR(Tax_Efficient_Status?="Not Efficient",Tax_Efficient_Status?="Federal Only"),(Unstructured!I114+Unstructured!I115),I114) -> 5142.3978 | J45: =IF(OR(Tax_Efficient_Status?="Not Efficient",Tax_Efficient_Status?="Federal Only"),(Unstructured!J114+Unstructured!J115),J114) -> 0 | K45: =IF(OR(Tax_Efficient_Status?="Not Efficient",Tax_Efficient_Status?="Federal Only"),(Unstructured!K114+Unstructured!K115),K114) -> 0 | ... AB45: =IF(OR(Tax_Efficient_Status?="Not Efficient",Tax_Efficient_Status?="Federal Only"),(Unstructured!AB114+Unstructured!AB115),AB114) -> 0
B46: Federal | D46: =IF(Tax_Efficient_Status?="Not Efficient",(Unstructured!D121+Unstructured!D122),D121) -> 17855.548 | E46: =IF(Tax_Efficient_Status?="Not Efficient",(Unstructured!E121+Unstructured!E122),E121) -> 28568.877 | F46: =IF(Tax_Efficient_Status?="Not Efficient",(Unstructured!F121+Unstructured!F122),F121) -> 17141.326 | G46: =IF(Tax_Efficient_Status?="Not Efficient",(Unstructured!G121+Unstructured!G122),G121) -> 10284.796 | H46: =IF(Tax_Efficient_Status?="Not Efficient",(Unstructured!H121+Unstructured!H122),H121) -> 10284.796 | I46: =IF(Tax_Efficient_Status?="Not Efficient",(Unstructured!I121+Unstructured!I122),I121) -> 5142.3978 | J46: =IF(Tax_Efficient_Status?="Not Efficient",(Unstructured!J121+Unstructured!J122),J121) -> 0 | K46: =IF(Tax_Efficient_Status?="Not Efficient",(Unstructured!K121+Unstructured!K122),K121) -> 0 | ... AB46: =IF(Tax_Efficient_Status?="Not Efficient",(Unstructured!AB121+Unstructured!AB122),AB121) -> 0
B48: State Tax
B49: State Taxable Income | D49: =D30-(D38+D42+D45) -> -13071.734 | E49: =E30-(E38+E42+E45) -> -23690.169 | F49: =F30-(F38+F42+F45) -> -12165.841 | G49: =G30-(G38+G42+G45) -> -5210.6145 | H49: =H30-(H38+H42+H45) -> -5109.9603 | I49: =I30-(I38+I42+I45) -> 135.08819 | J49: =J30-(J38+J42+J45) -> 5382.1729 | K49: =K30-(K38+K42+K45) -> 5488.9365 | ... AB49: =AB30-(AB38+AB42+AB45) -> 7664.9139
B50: State Taxes | D50: =IF(AND(Owner_is_Taxpayer_Non_Taxpayer?="Taxpayer",D49>0),D49*State_Income_Tax_Rate,0) -> 0 | E50: =IF(AND(Owner_is_Taxpayer_Non_Taxpayer?="Taxpayer",E49>0),E49*State_Income_Tax_Rate,0) -> 0 | F50: =IF(AND(Owner_is_Taxpayer_Non_Taxpayer?="Taxpayer",F49>0),F49*State_Income_Tax_Rate,0) -> 0 | G50: =IF(AND(Owner_is_Taxpayer_Non_Taxpayer?="Taxpayer",G49>0),G49*State_Income_Tax_Rate,0) -> 0 | H50: =IF(AND(Owner_is_Taxpayer_Non_Taxpayer?="Taxpayer",H49>0),H49*State_Income_Tax_Rate,0) -> 0 | I50: =IF(AND(Owner_is_Taxpayer_Non_Taxpayer?="Taxpayer",I49>0),I49*State_Income_Tax_Rate,0) -> 3.3772048 | J50: =IF(AND(Owner_is_Taxpayer_Non_Taxpayer?="Taxpayer",J49>0),J49*State_Income_Tax_Rate,0) -> 134.55432 | K50: =IF(AND(Owner_is_Taxpayer_Non_Taxpayer?="Taxpayer",K49>0),K49*State_Income_Tax_Rate,0) -> 137.22341 | ... AB50: =IF(AND(Owner_is_Taxpayer_Non_Taxpayer?="Taxpayer",AB49>0),AB49*State_Income_Tax_Rate,0) -> 191.62285
B51: Gross State Tax Credit | D51: =IF(AND(State_ITC_On_Off?="On",D17=1),(State_Tax_Credit_Rate*State_Tax_Credit_Basis),0) -> 0 | E51: =IF(Tax_Efficient_Status?="Not Efficient",D52,0) -> 0 | F51: =IF(Tax_Efficient_Status?="Not Efficient",E52,0) -> 0 | G51: =IF(Tax_Efficient_Status?="Not Efficient",F52,0) -> 0 | H51: =IF(Tax_Efficient_Status?="Not Efficient",G52,0) -> 0 | I51: =IF(Tax_Efficient_Status?="Not Efficient",H52,0) -> 0 | J51: =IF(Tax_Efficient_Status?="Not Efficient",I52,0) -> 0 | K51: =IF(Tax_Efficient_Status?="Not Efficient",J52,0) -> 0 | L51: =IF(Tax_Efficient_Status?="Not Efficient",K52,0) -> 0 | ... AB51: =IF(Tax_Efficient_Status?="Not Efficient",AA52,0) -> 0
B52: Net State Tax Credit | D52: =IF(D51>D50,D51-D50,0) -> 0 | E52: =IF(Tax_Efficient_Status?="Not Efficient",IF(E51>E50,E51-E50,0),0) -> 0 | F52: =IF(Tax_Efficient_Status?="Not Efficient",IF(F51>F50,F51-F50,0),0) -> 0 | G52: =IF(Tax_Efficient_Status?="Not Efficient",IF(G51>G50,G51-G50,0),0) -> 0 | H52: =IF(Tax_Efficient_Status?="Not Efficient",IF(H51>H50,H51-H50,0),0) -> 0 | I52: =IF(Tax_Efficient_Status?="Not Efficient",IF(I51>I50,I51-I50,0),0) -> 0 | J52: =IF(Tax_Efficient_Status?="Not Efficient",IF(J51>J50,J51-J50,0),0) -> 0 | K52: =IF(Tax_Efficient_Status?="Not Efficient",IF(K51>K50,K51-K50,0),0) -> 0 | L52: =IF(Tax_Efficient_Status?="Not Efficient",IF(L51>L50,L51-L50,0),0) -> 0 | ... AB52: =IF(Tax_Efficient_Status?="Not Efficient",IF(AB51>AB50,AB51-AB50,0),0) -> 0
B53: Net State Taxes Due | D53: =D50 -> 0 | E53: =E50 -> 0 | F53: =F50 -> 0 | G53: =G50 -> 0 | H53: =H50 -> 0 | I53: =I50 -> 3.3772048 | J53: =J50 -> 134.55432 | K53: =K50 -> 137.22341 | ... AB53: =AB50 -> 191.62285
B55: Federal Tax
B56: Federal Taxable Income | D56: =D30-(D38+D42+D46+D53) -> -13071.734 | E56: =E30-(E38+E42+E46+E53) -> -23690.169 | F56: =F30-(F38+F42+F46+F53) -> -12165.841 | G56: =G30-(G38+G42+G46+G53) -> -5210.6145 | H56: =H30-(H38+H42+H46+H53) -> -5109.9603 | I56: =I30-(I38+I42+I46+I53) -> 131.71099 | J56: =J30-(J38+J42+J46+J53) -> 5247.6186 | K56: =K30-(K38+K42+K46+K53) -> 5351.7131 | ... AB56: =AB30-(AB38+AB42+AB46+AB53) -> 7473.2911
B57: Federal Taxes | D57: =IF(AND(Owner_is_Taxpayer_Non_Taxpayer?="Taxpayer",D56>0),D56*Taxpayer_Marginal_Rate,0) -> 0 | E57: =IF(AND(Owner_is_Taxpayer_Non_Taxpayer?="Taxpayer",E56>0),E56*Taxpayer_Marginal_Rate,0) -> 0 | F57: =IF(AND(Owner_is_Taxpayer_Non_Taxpayer?="Taxpayer",F56>0),F56*Taxpayer_Marginal_Rate,0) -> 0 | G57: =IF(AND(Owner_is_Taxpayer_Non_Taxpayer?="Taxpayer",G56>0),G56*Taxpayer_Marginal_Rate,0) -> 0 | H57: =IF(AND(Owner_is_Taxpayer_Non_Taxpayer?="Taxpayer",H56>0),H56*Taxpayer_Marginal_Rate,0) -> 0 | I57: =IF(AND(Owner_is_Taxpayer_Non_Taxpayer?="Taxpayer",I56>0),I56*Taxpayer_Marginal_Rate,0) -> 27.659308 | J57: =IF(AND(Owner_is_Taxpayer_Non_Taxpayer?="Taxpayer",J56>0),J56*Taxpayer_Marginal_Rate,0) -> 1101.9999 | K57: =IF(AND(Owner_is_Taxpayer_Non_Taxpayer?="Taxpayer",K56>0),K56*Taxpayer_Marginal_Rate,0) -> 1123.8597 | ... AB57: =IF(AND(Owner_is_Taxpayer_Non_Taxpayer?="Taxpayer",AB56>0),AB56*Taxpayer_Marginal_Rate,0) -> 1569.3911
B58: Gross Federal ITC | D58: =IF(AND(Tax_Credit_Selector_ITC_or_PTC="ITC",Federal_ITC_Cash_Sale_OnOff="Off",D17=1),Federal_ITC_Dollar_Value,0) -> 31509.79 | E58: =IF(Tax_Efficient_Status?="Not Efficient",D59,0) -> 0 | F58: =IF(Tax_Efficient_Status?="Not Efficient",E59,0) -> 0 | G58: =IF(Tax_Efficient_Status?="Not Efficient",F59,0) -> 0 | H58: =IF(Tax_Efficient_Status?="Not Efficient",G59,0) -> 0 | I58: =IF(Tax_Efficient_Status?="Not Efficient",H59,0) -> 0 | J58: =IF(Tax_Efficient_Status?="Not Efficient",I59,0) -> 0 | K58: =IF(Tax_Efficient_Status?="Not Efficient",J59,0) -> 0 | L58: =IF(Tax_Efficient_Status?="Not Efficient",K59,0) -> 0 | ... AB58: =IF(Tax_Efficient_Status?="Not Efficient",AA59,0) -> 0
B59: Net Federal ITC | D59: =IF(D58>D57,D58-D57,0) -> 31509.79 | E59: =IF(Tax_Efficient_Status?="Not Efficient",IF(E58>E57,E58-E57,0),0) -> 0 | F59: =IF(Tax_Efficient_Status?="Not Efficient",IF(F58>F57,F58-F57,0),0) -> 0 | G59: =IF(Tax_Efficient_Status?="Not Efficient",IF(G58>G57,G58-G57,0),0) -> 0 | H59: =IF(Tax_Efficient_Status?="Not Efficient",IF(H58>H57,H58-H57,0),0) -> 0 | I59: =IF(Tax_Efficient_Status?="Not Efficient",IF(I58>I57,I58-I57,0),0) -> 0 | J59: =IF(Tax_Efficient_Status?="Not Efficient",IF(J58>J57,J58-J57,0),0) -> 0 | K59: =IF(Tax_Efficient_Status?="Not Efficient",IF(K58>K57,K58-K57,0),0) -> 0 | L59: =IF(Tax_Efficient_Status?="Not Efficient",IF(L58>L57,L58-L57,0),0) -> 0 | ... AB59: =IF(Tax_Efficient_Status?="Not Efficient",IF(AB58>AB57,AB58-AB57,0),0) -> 0
B60: Net Federal Taxes Due | D60: =IF(D58>D57,0,D57-D58) -> 0 | E60: =IF(E58>E57,0,E57-E58) -> 0 | F60: =IF(F58>F57,0,F57-F58) -> 0 | G60: =IF(G58>G57,0,G57-G58) -> 0 | H60: =IF(H58>H57,0,H57-H58) -> 0 | I60: =IF(I58>I57,0,I57-I58) -> 27.659308 | J60: =IF(J58>J57,0,J57-J58) -> 1101.9999 | K60: =IF(K58>K57,0,K57-K58) -> 1123.8597 | ... AB60: =IF(AB58>AB57,0,AB57-AB58) -> 1569.3911
B62: Project Net Income | D62: =(D56-D60) -> -13071.734 | E62: =(E56-E60) -> -23690.169 | F62: =(F56-F60) -> -12165.841 | G62: =(G56-G60) -> -5210.6145 | H62: =(H56-H60) -> -5109.9603 | I62: =(I56-I60) -> 104.05168 | J62: =(J56-J60) -> 4145.6187 | K62: =(K56-K60) -> 4227.8533 | ... AB62: =(AB56-AB60) -> 5903.9
B66: Valuation Analysis
B67: Year | C67: 0 | D67: =C67+1 -> 1 | E67: =D67+1 -> 2 | F67: =E67+1 -> 3 | G67: =F67+1 -> 4 | H67: =G67+1 -> 5 | I67: =H67+1 -> 6 | J67: =I67+1 -> 7 | K67: =J67+1 -> 8 | ... AB67: =AA67+1 -> 25
B68: After-Tax Excess Benefits
B69: Net Federal ITC | D69: =IF(OR(Owner_is_Taxpayer_Non_Taxpayer?="Non-Taxpayer",Tax_Efficient_Status?="Not Efficient", Tax_Credit_Selector_ITC_or_PTC="PTC",Federal_ITC_Cash_Sale_OnOff="On"),0,Unstructured!D59) -> 31509.79
B70: After-tax Excess Federal Depreciation | D70: =IF(OR(Owner_is_Taxpayer_Non_Taxpayer?="Taxpayer",Tax_Efficient_Status?="State & Federal", Tax_Efficient_Status?="Federal Only"),D124*(Taxpayer_Marginal_Rate),0) -> 2745.0642 | E70: =IF(OR(Owner_is_Taxpayer_Non_Taxpayer?="Taxpayer",Tax_Efficient_Status?="State & Federal", Tax_Efficient_Status?="Federal Only"),E124*(Taxpayer_Marginal_Rate),0) -> 4974.9354 | F70: =IF(OR(Owner_is_Taxpayer_Non_Taxpayer?="Taxpayer",Tax_Efficient_Status?="State & Federal", Tax_Efficient_Status?="Federal Only"),F124*(Taxpayer_Marginal_Rate),0) -> 2554.8267 | G70: =IF(OR(Owner_is_Taxpayer_Non_Taxpayer?="Taxpayer",Tax_Efficient_Status?="State & Federal", Tax_Efficient_Status?="Federal Only"),G124*(Taxpayer_Marginal_Rate),0) -> 1094.229 | H70: =IF(OR(Owner_is_Taxpayer_Non_Taxpayer?="Taxpayer",Tax_Efficient_Status?="State & Federal", Tax_Efficient_Status?="Federal Only"),H124*(Taxpayer_Marginal_Rate),0) -> 1073.0917 | I70: =IF(OR(Owner_is_Taxpayer_Non_Taxpayer?="Taxpayer",Tax_Efficient_Status?="State & Federal", Tax_Efficient_Status?="Federal Only"),I124*(Taxpayer_Marginal_Rate),0) -> 0 | J70: =IF(OR(Owner_is_Taxpayer_Non_Taxpayer?="Taxpayer",Tax_Efficient_Status?="State & Federal", Tax_Efficient_Status?="Federal Only"),J124*(Taxpayer_Marginal_Rate),0) -> 0 | K70: =IF(OR(Owner_is_Taxpayer_Non_Taxpayer?="Taxpayer",Tax_Efficient_Status?="State & Federal", Tax_Efficient_Status?="Federal Only"),K124*(Taxpayer_Marginal_Rate),0) -> 0 | ... AB70: =IF(OR(Owner_is_Taxpayer_Non_Taxpayer?="Taxpayer",Tax_Efficient_Status?="State & Federal", Tax_Efficient_Status?="Federal Only"),AB124*(Taxpayer_Marginal_Rate),0) -> 0
B71: Net State Tax Credot | D71: =IF(OR(Owner_is_Taxpayer_Non_Taxpayer?="Non-Taxpayer",Tax_Efficient_Status?="Not Efficient"),0,D52) -> 0
B72: After-Tax Excess State Depreciation | D72: =IF(OR(Owner_is_Taxpayer_Non_Taxpayer?="Taxpayer",Tax_Efficient_Status?="State & Federal"),D117*State_Income_Tax_Rate*(1-Taxpayer_Marginal_Rate),0) -> 258.16675 | E72: =IF(OR(Owner_is_Taxpayer_Non_Taxpayer?="Taxpayer",Tax_Efficient_Status?="State & Federal"),E117*State_Income_Tax_Rate*(1-Taxpayer_Marginal_Rate),0) -> 467.88083 | F72: =IF(OR(Owner_is_Taxpayer_Non_Taxpayer?="Taxpayer",Tax_Efficient_Status?="State & Federal"),F117*State_Income_Tax_Rate*(1-Taxpayer_Marginal_Rate),0) -> 240.27536 | G72: =IF(OR(Owner_is_Taxpayer_Non_Taxpayer?="Taxpayer",Tax_Efficient_Status?="State & Federal"),G117*State_Income_Tax_Rate*(1-Taxpayer_Marginal_Rate),0) -> 102.90964 | H72: =IF(OR(Owner_is_Taxpayer_Non_Taxpayer?="Taxpayer",Tax_Efficient_Status?="State & Federal"),H117*State_Income_Tax_Rate*(1-Taxpayer_Marginal_Rate),0) -> 100.92172 | I72: =IF(OR(Owner_is_Taxpayer_Non_Taxpayer?="Taxpayer",Tax_Efficient_Status?="State & Federal"),I117*State_Income_Tax_Rate*(1-Taxpayer_Marginal_Rate),0) -> 0 | J72: =IF(OR(Owner_is_Taxpayer_Non_Taxpayer?="Taxpayer",Tax_Efficient_Status?="State & Federal"),J117*State_Income_Tax_Rate*(1-Taxpayer_Marginal_Rate),0) -> 0 | K72: =IF(OR(Owner_is_Taxpayer_Non_Taxpayer?="Taxpayer",Tax_Efficient_Status?="State & Federal"),K117*State_Income_Tax_Rate*(1-Taxpayer_Marginal_Rate),0) -> 0 | ... AB72: =IF(OR(Owner_is_Taxpayer_Non_Taxpayer?="Taxpayer",Tax_Efficient_Status?="State & Federal"),AB117*State_Income_Tax_Rate*(1-Taxpayer_Marginal_Rate),0) -> 0
B73: Total After-Tax Benefits | D73: =SUM(D69:D72) -> 34513.021 | E73: =SUM(E69:E72) -> 5442.8162 | F73: =SUM(F69:F72) -> 2795.102 | G73: =SUM(G69:G72) -> 1197.1387 | H73: =SUM(H69:H72) -> 1174.0134 | I73: =SUM(I69:I72) -> 0 | J73: =SUM(J69:J72) -> 0 | K73: =SUM(K69:K72) -> 0 | ... AB73: =SUM(AB69:AB72) -> 0
B75: Debt Principal Payments (Cash Reduction) | D75: =IF(Project_Debt?="Yes",-Unstructured!D100,0) -> 0 | E75: =IF(Project_Debt?="Yes",-Unstructured!E100,0) -> 0 | F75: =IF(Project_Debt?="Yes",-Unstructured!F100,0) -> 0 | G75: =IF(Project_Debt?="Yes",-Unstructured!G100,0) -> 0 | H75: =IF(Project_Debt?="Yes",-Unstructured!H100,0) -> 0 | I75: =IF(Project_Debt?="Yes",-Unstructured!I100,0) -> 0 | J75: =IF(Project_Debt?="Yes",-Unstructured!J100,0) -> 0 | K75: =IF(Project_Debt?="Yes",-Unstructured!K100,0) -> 0 | ... AB75: =IF(Project_Debt?="Yes",-Unstructured!AB100,0) -> 0
B76: ITC Cash Sale Proceeds (Cash Inflow) | D76: =IF(AND(Tax_Credit_Selector_ITC_or_PTC="ITC", D67>=ITC_Cash_Sale_First_Year_Payment,D$67<=(ITC_Cash_Sale_Number_of_Annual_Payments+1),Federal_ITC_Cash_Sale_OnOff="On", SUM($C$76:C76)<(1-ITC_Cash_Sale_Discount_to_Purchase_Price)*Federal_ITC_Dollar_Value), Federal_ITC_Dollar_Value/ITC_Cash_Sale_Number_of_Annual_Payments*(1-ITC_Cash_Sale_Discount_to_Purchase_Price),0) -> 0 | E76: =IF(AND(Tax_Credit_Selector_ITC_or_PTC="ITC", E67>=ITC_Cash_Sale_First_Year_Payment,E$67<=(ITC_Cash_Sale_Number_of_Annual_Payments+1),Federal_ITC_Cash_Sale_OnOff="On", SUM($C$76:D76)<(1-ITC_Cash_Sale_Discount_to_Purchase_Price)*Federal_ITC_Dollar_Value), Federal_ITC_Dollar_Value/ITC_Cash_Sale_Number_of_Annual_Payments*(1-ITC_Cash_Sale_Discount_to_Purchase_Price),0) -> 0 | F76: =IF(AND(Tax_Credit_Selector_ITC_or_PTC="ITC", F67>=ITC_Cash_Sale_First_Year_Payment,F$67<=(ITC_Cash_Sale_Number_of_Annual_Payments+1),Federal_ITC_Cash_Sale_OnOff="On", SUM($C$76:E76)<(1-ITC_Cash_Sale_Discount_to_Purchase_Price)*Federal_ITC_Dollar_Value), Federal_ITC_Dollar_Value/ITC_Cash_Sale_Number_of_Annual_Payments*(1-ITC_Cash_Sale_Discount_to_Purchase_Price),0) -> 0 | G76: =IF(AND(Tax_Credit_Selector_ITC_or_PTC="ITC", G67>=ITC_Cash_Sale_First_Year_Payment,G$67<=(ITC_Cash_Sale_Number_of_Annual_Payments+1),Federal_ITC_Cash_Sale_OnOff="On", SUM($C$76:F76)<(1-ITC_Cash_Sale_Discount_to_Purchase_Price)*Federal_ITC_Dollar_Value), Federal_ITC_Dollar_Value/ITC_Cash_Sale_Number_of_Annual_Payments*(1-ITC_Cash_Sale_Discount_to_Purchase_Price),0) -> 0 | H76: =IF(AND(Tax_Credit_Selector_ITC_or_PTC="ITC", H67>=ITC_Cash_Sale_First_Year_Payment,H$67<=(ITC_Cash_Sale_Number_of_Annual_Payments+1),Federal_ITC_Cash_Sale_OnOff="On", SUM($C$76:G76)<(1-ITC_Cash_Sale_Discount_to_Purchase_Price)*Federal_ITC_Dollar_Value), Federal_ITC_Dollar_Value/ITC_Cash_Sale_Number_of_Annual_Payments*(1-ITC_Cash_Sale_Discount_to_Purchase_Price),0) -> 0 | I76: =IF(AND(Tax_Credit_Selector_ITC_or_PTC="ITC", I67>=ITC_Cash_Sale_First_Year_Payment,I$67<=(ITC_Cash_Sale_Number_of_Annual_Payments+1),Federal_ITC_Cash_Sale_OnOff="On", SUM($C$76:H76)<(1-ITC_Cash_Sale_Discount_to_Purchase_Price)*Federal_ITC_Dollar_Value), Federal_ITC_Dollar_Value/ITC_Cash_Sale_Number_of_Annual_Payments*(1-ITC_Cash_Sale_Discount_to_Purchase_Price),0) -> 0 | J76: =IF(AND(Tax_Credit_Selector_ITC_or_PTC="ITC", J67>=ITC_Cash_Sale_First_Year_Payment,J$67<=(ITC_Cash_Sale_Number_of_Annual_Payments+1),Federal_ITC_Cash_Sale_OnOff="On", SUM($C$76:I76)<(1-ITC_Cash_Sale_Discount_to_Purchase_Price)*Federal_ITC_Dollar_Value), Federal_ITC_Dollar_Value/ITC_Cash_Sale_Number_of_Annual_Payments*(1-ITC_Cash_Sale_Discount_to_Purchase_Price),0) -> 0 | K76: =IF(AND(Tax_Credit_Selector_ITC_or_PTC="ITC", K67>=ITC_Cash_Sale_First_Year_Payment,K$67<=(ITC_Cash_Sale_Number_of_Annual_Payments+1),Federal_ITC_Cash_Sale_OnOff="On", SUM($C$76:J76)<(1-ITC_Cash_Sale_Discount_to_Purchase_Price)*Federal_ITC_Dollar_Value), Federal_ITC_Dollar_Value/ITC_Cash_Sale_Number_of_Annual_Payments*(1-ITC_Cash_Sale_Discount_to_Purchase_Price),0) -> 0 | ... AB76: =IF(AND(Tax_Credit_Selector_ITC_or_PTC="ITC", AB67>=ITC_Cash_Sale_First_Year_Payment,AB$67<=(ITC_Cash_Sale_Number_of_Annual_Payments+1),Federal_ITC_Cash_Sale_OnOff="On", SUM($C$76:AA76)<(1-ITC_Cash_Sale_Discount_to_Purchase_Price)*Federal_ITC_Dollar_Value), Federal_ITC_Dollar_Value/ITC_Cash_Sale_Number_of_Annual_Payments*(1-ITC_Cash_Sale_Discount_to_Purchase_Price),0) -> 0
B77: PTC Alternative to ITC (Cash inflow) | D77: =IF(AND(Tax_Credit_Selector_ITC_or_PTC="PTC",COUNTIF($C$77:$C77,">0")<PTC_Term_in_Years),D22*D23,0) -> 0 | E77: =IF(AND(Tax_Credit_Selector_ITC_or_PTC="PTC",COUNTIF($C$77:$C77,">0")<PTC_Term_in_Years),E22*E23,0) -> 0 | F77: =IF(AND(Tax_Credit_Selector_ITC_or_PTC="PTC",COUNTIF($C$77:$C77,">0")<PTC_Term_in_Years),F22*F23,0) -> 0 | G77: =IF(AND(Tax_Credit_Selector_ITC_or_PTC="PTC",COUNTIF($C$77:$C77,">0")<PTC_Term_in_Years),G22*G23,0) -> 0 | H77: =IF(AND(Tax_Credit_Selector_ITC_or_PTC="PTC",COUNTIF($C$77:$C77,">0")<PTC_Term_in_Years),H22*H23,0) -> 0 | I77: =IF(AND(Tax_Credit_Selector_ITC_or_PTC="PTC",COUNTIF($C$77:$C77,">0")<PTC_Term_in_Years),I22*I23,0) -> 0 | J77: =IF(AND(Tax_Credit_Selector_ITC_or_PTC="PTC",COUNTIF($C$77:$C77,">0")<PTC_Term_in_Years),J22*J23,0) -> 0 | K77: =IF(AND(Tax_Credit_Selector_ITC_or_PTC="PTC",COUNTIF($C$77:$C77,">0")<PTC_Term_in_Years),K22*K23,0) -> 0 | ... AB77: =IF(AND(Tax_Credit_Selector_ITC_or_PTC="PTC",COUNTIF($C$77:$C77,">0")<PTC_Term_in_Years),AB22*AB23,0) -> 0
B79: Cash on Cash Analysis | AD79: UNIQUE FORMULA THIS CELL: See Termination Payment Selector, Dashboard Cell D74
B80: Cash Only Flow | C80: =-Project_Net_Investment -> -114975.09 | D80: =(D62+D46+SUM(D75:D77)) -> 4783.8136 | E80: =(E62+E46+SUM(E75:E77)) -> 4878.7079 | F80: =(F62+F46+SUM(F75:F77)) -> 4975.4846 | G80: =(G62+G46+SUM(G75:G77)) -> 5074.181 | H80: =(H62+H46+SUM(H75:H77)) -> 5174.8352 | I80: =(I62+I46+SUM(I75:I77)) -> 5246.4495 | J80: =(J62+J46+SUM(J75:J77)) -> 4145.6187 | K80: =(K62+K46+SUM(K75:K77)) -> 4227.8533 | ... AA80: =(AA62+AA46+SUM(AA75:AA77)) -> 5789.0657 | AB80: =((AB62+AB46+SUM(AB75:AB77))+IF(Termination_Value_OnOff="On",INDEX(Termination_Value_Table_End_of_Term,2,MATCH(Termination_Value_Percentage,Dashboard!C72:E72,0)),0)) -> 23150.163
B81: Cumulative Cash Flow | C81: =C80 -> -114975.09 | D81: =C81+D80 -> -110191.28 | E81: =D81+E80 -> -105312.57 | F81: =E81+F80 -> -100337.08 | G81: =F81+G80 -> -95262.903 | H81: =G81+H80 -> -90088.068 | I81: =H81+I80 -> -84841.618 | J81: =I81+J80 -> -80695.999 | K81: =J81+K80 -> -76468.146 | ... AB81: =AA81+AB80 -> 26947.412
B82: Cash Only Flow NPV | C82: =NPV(Investor_Discount_Rate,D80:AB80)+C80 -> -51880.788
B83: Cash Only Flow IRR | C83: =IRR(C80:AB80) -> 0.0147451
B84: Cash Flow Test | C84: =IF(SUM(D84:AB84)>0,"Fail","Pass") -> Pass | D84: =IF(D80>0,0,1) -> 0 | E84: =IF(E80>0,0,1) -> 0 | F84: =IF(F80>0,0,1) -> 0 | G84: =IF(G80>0,0,1) -> 0 | H84: =IF(H80>0,0,1) -> 0 | I84: =IF(I80>0,0,1) -> 0 | J84: =IF(J80>0,0,1) -> 0 | K84: =IF(K80>0,0,1) -> 0 | ... AB84: =IF(AB80>0,0,1) -> 0
B86: Cash and Tax Benefits Analysis | AD86: UNIQUE FORMULA THIS CELL: See Termination Payment Selector, Dashboard Cell D74
B87: Cash & Tax Benefits Flows | C87: =-Project_Net_Investment -> -114975.09 | D87: =(D62+D46+D73+SUM(D75:D77)) -> 39296.835 | E87: =(E62+E46+E73+SUM(E75:E77)) -> 10321.524 | F87: =(F62+F46+F73+SUM(F75:F77)) -> 7770.5867 | G87: =(G62+G46+G73+SUM(G75:G77)) -> 6271.3197 | H87: =(H62+H46+H73+SUM(H75:H77)) -> 6348.8486 | I87: =(I62+I46+I73+SUM(I75:I77)) -> 5246.4495 | J87: =(J62+J46+J73+SUM(J75:J77)) -> 4145.6187 | K87: =(K62+K46+K73+SUM(K75:K77)) -> 4227.8533 | ... AA87: =(AA62+AA46+AA73+SUM(AA75:AA77)) -> 5789.0657 | AB87: =((AB62+AB46+AB73++SUM(AB75:AB77))-AB75)++IF(Termination_Value_OnOff="On",INDEX(Termination_Value_Table_End_of_Term,2,MATCH(Termination_Value_Percentage,Dashboard!C72:E72,0)),0) -> 23150.163
B88: Cumulative Flows | C88: =C87 -> -114975.09 | D88: =C88+D87 -> -75678.255 | E88: =D88+E87 -> -65356.731 | F88: =E88+F87 -> -57586.144 | G88: =F88+G87 -> -51314.825 | H88: =G88+H87 -> -44965.976 | I88: =H88+I87 -> -39719.527 | J88: =I88+J87 -> -35573.908 | K88: =J88+K87 -> -31346.055 | ... AB88: =AA88+AB87 -> 72069.504
B89: NPV | C89: =NPV(Investor_Discount_Rate,D87:AB87)+C87 -> -10574.11
B90: IRR | C90: =IRR(C87:AB87) -> 0.051457314
B94: Debt Management Economics
B95: Year | C95: 0 | D95: 1 | E95: 2 | F95: 3 | G95: 4 | H95: 5 | I95: 6 | J95: 7 | K95: 8 | L95: 9 | M95: 10 | N95: 11 | O95: 12 | P95: 13 | Q95: 14 | R95: 15 | S95: 16 | T95: 17 | U95: 18 | V95: 19 | W95: 20 | X95: 21 | Y95: 22 | Z95: 23 | AA95: 24 | AB95: 25
B96: Amortizing Debt
B97: Debt Management Calculations
B98: Annual Amoritzation Payment | D98: =IF(Project_Debt?="Yes",IF(Unstructured!D$17<=Project_Loan_Term?,PMT(Project_Loan_Rate,Project_Loan_Term?,-Project_Loan_Amount,0),0),0) -> 0 | E98: =IF(Project_Debt?="Yes",IF(Unstructured!E$17<=Project_Loan_Term?,PMT(Project_Loan_Rate,Project_Loan_Term?,-Project_Loan_Amount,0),0),0) -> 0 | F98: =IF(Project_Debt?="Yes",IF(Unstructured!F$17<=Project_Loan_Term?,PMT(Project_Loan_Rate,Project_Loan_Term?,-Project_Loan_Amount,0),0),0) -> 0 | G98: =IF(Project_Debt?="Yes",IF(Unstructured!G$17<=Project_Loan_Term?,PMT(Project_Loan_Rate,Project_Loan_Term?,-Project_Loan_Amount,0),0),0) -> 0 | H98: =IF(Project_Debt?="Yes",IF(Unstructured!H$17<=Project_Loan_Term?,PMT(Project_Loan_Rate,Project_Loan_Term?,-Project_Loan_Amount,0),0),0) -> 0 | I98: =IF(Project_Debt?="Yes",IF(Unstructured!I$17<=Project_Loan_Term?,PMT(Project_Loan_Rate,Project_Loan_Term?,-Project_Loan_Amount,0),0),0) -> 0 | J98: =IF(Project_Debt?="Yes",IF(Unstructured!J$17<=Project_Loan_Term?,PMT(Project_Loan_Rate,Project_Loan_Term?,-Project_Loan_Amount,0),0),0) -> 0 | K98: =IF(Project_Debt?="Yes",IF(Unstructured!K$17<=Project_Loan_Term?,PMT(Project_Loan_Rate,Project_Loan_Term?,-Project_Loan_Amount,0),0),0) -> 0 | ... AB98: =IF(Project_Debt?="Yes",IF(Unstructured!AB$17<=Project_Loan_Term?,PMT(Project_Loan_Rate,Project_Loan_Term?,-Project_Loan_Amount,0),0),0) -> 0
B99: Interest Portion | D99: =C101*Project_Loan_Rate -> 0 | E99: =D101*Project_Loan_Rate -> 0 | F99: =E101*Project_Loan_Rate -> 0 | G99: =F101*Project_Loan_Rate -> 0 | H99: =G101*Project_Loan_Rate -> 0 | I99: =H101*Project_Loan_Rate -> 0 | J99: =I101*Project_Loan_Rate -> 0 | K99: =J101*Project_Loan_Rate -> 0 | ... AB99: =AA101*Project_Loan_Rate -> 0
B100: Principal Portion | D100: =D98-D99 -> 0 | E100: =E98-E99 -> 0 | F100: =F98-F99 -> 0 | G100: =G98-G99 -> 0 | H100: =H98-H99 -> 0 | I100: =I98-I99 -> 0 | J100: =J98-J99 -> 0 | K100: =K98-K99 -> 0 | ... AB100: =AB98-AB99 -> 0
B101: Remaining Balance | C101: =IF(Project_Debt?="Yes",Project_Loan_Amount,0) -> 0 | D101: =C101-D100 -> 0 | E101: =D101-E100 -> 0 | F101: =E101-F100 -> 0 | G101: =F101-G100 -> 0 | H101: =G101-H100 -> 0 | I101: =H101-I100 -> 0 | J101: =I101-J100 -> 0 | K101: =J101-K100 -> 0 | ... AB101: =AA101-AB100 -> 0
B103: Max Payment under Debt Coverage Ratio | D103: =(((Unstructured!D30*Production_Delta_P95_P50)-Unstructured!D38)/Project_Loan_Coverage_Ratio) -> 3626.883 | E103: =(((Unstructured!E30*Production_Delta_P95_P50)-Unstructured!E38)/Project_Loan_Coverage_Ratio) -> 3698.8202 | F103: =(((Unstructured!F30*Production_Delta_P95_P50)-Unstructured!F38)/Project_Loan_Coverage_Ratio) -> 3772.1841 | G103: =(((Unstructured!G30*Production_Delta_P95_P50)-Unstructured!G38)/Project_Loan_Coverage_Ratio) -> 3847.0032 | H103: =(((Unstructured!H30*Production_Delta_P95_P50)-Unstructured!H38)/Project_Loan_Coverage_Ratio) -> 3923.3062 | I103: =(((Unstructured!I30*Production_Delta_P95_P50)-Unstructured!I38)/Project_Loan_Coverage_Ratio) -> 4001.1227 | J103: =(((Unstructured!J30*Production_Delta_P95_P50)-Unstructured!J38)/Project_Loan_Coverage_Ratio) -> 4080.4825 | K103: =(((Unstructured!K30*Production_Delta_P95_P50)-Unstructured!K38)/Project_Loan_Coverage_Ratio) -> 4161.4164 | ... AB103: =(((Unstructured!AB30*Production_Delta_P95_P50)-Unstructured!AB38)/Project_Loan_Coverage_Ratio) -> 5810.9193
B104: Debt Coverage Test Delta | D104: =D103-D98 -> 3626.883 | E104: =E103-E98 -> 3698.8202 | F104: =F103-F98 -> 3772.1841 | G104: =G103-G98 -> 3847.0032 | H104: =H103-H98 -> 3923.3062 | I104: =I103-I98 -> 4001.1227 | J104: =J103-J98 -> 4080.4825 | K104: =K103-K98 -> 4161.4164 | ... AB104: =AB103-AB98 -> 5810.9193
B105: Debt Coverage Ratio Test | C105: =IF(Dashboard!$H$27="Yes",IF(SUM(D105:W105)<0,"Fail","Pass"),"N/A") -> N/A | D105: =IF(D104<0,D104,0) -> 0 | E105: =IF(E104<0,D105+E104,D105+0) -> 0 | F105: =IF(F104<0,E105+F104,E105+0) -> 0 | G105: =IF(G104<0,F105+G104,F105+0) -> 0 | H105: =IF(H104<0,G105+H104,G105+0) -> 0 | I105: =IF(I104<0,H105+I104,H105+0) -> 0 | J105: =IF(J104<0,I105+J104,I105+0) -> 0 | K105: =IF(K104<0,J105+K104,J105+0) -> 0 | L105: =IF(L104<0,K105+L104,K105+0) -> 0 | ... AB105: =IF(AB104<0,AA105+AB104,AA105+0) -> 0
B106: Debt Amortization Test | C106: =IF(Project_Debt?="Yes",IF(MIN(D101:W101)<1,"Yes","No"),"N/A") -> N/A
B109: Depreciation Economics | D109: 1
B110: Year | C110: 0 | D110: 1 | E110: 2 | F110: 3 | G110: 4 | H110: 5 | I110: 6 | J110: 7 | K110: 8 | L110: 9 | M110: 10 | N110: 11 | O110: 12 | P110: 13 | Q110: 14 | R110: 15 | S110: 16 | T110: 17 | U110: 18 | V110: 19 | W110: 20 | X110: 21 | Y110: 22 | Z110: 23 | AA110: 24 | AB110: 25
B112: State Depreciation
B113: State Earnings, pre- Depreciation | D113: =Unstructured!D30-(Unstructured!D38+Unstructured!D42) -> 4783.8136 | E113: =Unstructured!E30-(Unstructured!E38+Unstructured!E42) -> 4878.7079 | F113: =Unstructured!F30-(Unstructured!F38+Unstructured!F42) -> 4975.4846 | G113: =Unstructured!G30-(Unstructured!G38+Unstructured!G42) -> 5074.181 | H113: =Unstructured!H30-(Unstructured!H38+Unstructured!H42) -> 5174.8352 | I113: =Unstructured!I30-(Unstructured!I38+Unstructured!I42) -> 5277.486 | J113: =Unstructured!J30-(Unstructured!J38+Unstructured!J42) -> 5382.1729 | K113: =Unstructured!K30-(Unstructured!K38+Unstructured!K42) -> 5488.9365 | ... AB113: =Unstructured!AB30-(Unstructured!AB38+Unstructured!AB42) -> 7664.9139
B114: Current Year State Depreciation | D114: =IF(AND(Owner_is_Taxpayer_Non_Taxpayer?="Taxpayer",Unstructured!D17<7),VLOOKUP(Unstructured!D17,Depreciation_Table,4),0) -> 17855.548 | E114: =IF(AND(Owner_is_Taxpayer_Non_Taxpayer?="Taxpayer",Unstructured!E17<7),VLOOKUP(Unstructured!E17,Depreciation_Table,4),0) -> 28568.877 | F114: =IF(AND(Owner_is_Taxpayer_Non_Taxpayer?="Taxpayer",Unstructured!F17<7),VLOOKUP(Unstructured!F17,Depreciation_Table,4),0) -> 17141.326 | G114: =IF(AND(Owner_is_Taxpayer_Non_Taxpayer?="Taxpayer",Unstructured!G17<7),VLOOKUP(Unstructured!G17,Depreciation_Table,4),0) -> 10284.796 | H114: =IF(AND(Owner_is_Taxpayer_Non_Taxpayer?="Taxpayer",Unstructured!H17<7),VLOOKUP(Unstructured!H17,Depreciation_Table,4),0) -> 10284.796 | I114: =IF(AND(Owner_is_Taxpayer_Non_Taxpayer?="Taxpayer",Unstructured!I17<7),VLOOKUP(Unstructured!I17,Depreciation_Table,4),0) -> 5142.3978 | J114: =IF(AND(Owner_is_Taxpayer_Non_Taxpayer?="Taxpayer",Unstructured!J17<7),VLOOKUP(Unstructured!J17,Depreciation_Table,4),0) -> 0 | K114: =IF(AND(Owner_is_Taxpayer_Non_Taxpayer?="Taxpayer",Unstructured!K17<7),VLOOKUP(Unstructured!K17,Depreciation_Table,4),0) -> 0 | ... AB114: =IF(AND(Owner_is_Taxpayer_Non_Taxpayer?="Taxpayer",Unstructured!AB17<7),VLOOKUP(Unstructured!AB17,Depreciation_Table,4),0) -> 0
B115: Start State Carryforward Balance | D115: =IF(OR(Tax_Efficient_Status?="Federal Only",Tax_Efficient_Status?="Not Efficient"),C117,0) -> 0 | E115: =IF(OR(Tax_Efficient_Status?="Federal Only",Tax_Efficient_Status?="Not Efficient"),D117,0) -> 0 | F115: =IF(OR(Tax_Efficient_Status?="Federal Only",Tax_Efficient_Status?="Not Efficient"),E117,0) -> 0 | G115: =IF(OR(Tax_Efficient_Status?="Federal Only",Tax_Efficient_Status?="Not Efficient"),F117,0) -> 0 | H115: =IF(OR(Tax_Efficient_Status?="Federal Only",Tax_Efficient_Status?="Not Efficient"),G117,0) -> 0 | I115: =IF(OR(Tax_Efficient_Status?="Federal Only",Tax_Efficient_Status?="Not Efficient"),H117,0) -> 0 | J115: =IF(OR(Tax_Efficient_Status?="Federal Only",Tax_Efficient_Status?="Not Efficient"),I117,0) -> 0 | K115: =IF(OR(Tax_Efficient_Status?="Federal Only",Tax_Efficient_Status?="Not Efficient"),J117,0) -> 0 | ... AB115: =IF(OR(Tax_Efficient_Status?="Federal Only",Tax_Efficient_Status?="Not Efficient"),AA117,0) -> 0
B116: State Taxable Income | D116: =IF(D113>(D114+D115),D113-(D114+D115),0) -> 0 | E116: =IF(E113>(E114+E115),E113-(E114+E115),0) -> 0 | F116: =IF(F113>(F114+F115),F113-(F114+F115),0) -> 0 | G116: =IF(G113>(G114+G115),G113-(G114+G115),0) -> 0 | H116: =IF(H113>(H114+H115),H113-(H114+H115),0) -> 0 | I116: =IF(I113>(I114+I115),I113-(I114+I115),0) -> 135.08819 | J116: =IF(J113>(J114+J115),J113-(J114+J115),0) -> 5382.1729 | K116: =IF(K113>(K114+K115),K113-(K114+K115),0) -> 5488.9365 | ... AB116: =IF(AB113>(AB114+AB115),AB113-(AB114+AB115),0) -> 7664.9139
B117: Excess Current Year State Dep. | D117: =IF(D113>(D114+D115),0,(D114+D115)-D113) -> 13071.734 | E117: =IF(E113>(E114+E115),0,(E114+E115)-E113) -> 23690.169 | F117: =IF(F113>(F114+F115),0,(F114+F115)-F113) -> 12165.841 | G117: =IF(G113>(G114+G115),0,(G114+G115)-G113) -> 5210.6145 | H117: =IF(H113>(H114+H115),0,(H114+H115)-H113) -> 5109.9603 | I117: =IF(I113>(I114+I115),0,(I114+I115)-I113) -> 0 | J117: =IF(J113>(J114+J115),0,(J114+J115)-J113) -> 0 | K117: =IF(K113>(K114+K115),0,(K114+K115)-K113) -> 0 | ... AB117: =IF(AB113>(AB114+AB115),0,(AB114+AB115)-AB113) -> 0
B119: Federal Depreciation
B120: Fed. Earnings, pre- Depreciation | D120: =Unstructured!D30-(Unstructured!D38+Unstructured!D42+IF(D53>0,Unstructured!D53,0)) -> 4783.8136 | E120: =Unstructured!E30-(Unstructured!E38+Unstructured!E42+Unstructured!E53) -> 4878.7079 | F120: =Unstructured!F30-(Unstructured!F38+Unstructured!F42+Unstructured!F53) -> 4975.4846 | G120: =Unstructured!G30-(Unstructured!G38+Unstructured!G42+Unstructured!G53) -> 5074.181 | H120: =Unstructured!H30-(Unstructured!H38+Unstructured!H42+Unstructured!H53) -> 5174.8352 | I120: =Unstructured!I30-(Unstructured!I38+Unstructured!I42+Unstructured!I53) -> 5274.1088 | J120: =Unstructured!J30-(Unstructured!J38+Unstructured!J42+Unstructured!J53) -> 5247.6186 | K120: =Unstructured!K30-(Unstructured!K38+Unstructured!K42+Unstructured!K53) -> 5351.7131 | L120: =Unstructured!L30-(Unstructured!L38+Unstructured!L42+Unstructured!L53) -> 5457.8724 | ... AB120: =Unstructured!AB30-(Unstructured!AB38+Unstructured!AB42+Unstructured!AB53) -> 7473.2911
B121: Current Year Fed. Depreciation | D121: =IF(AND(Owner_is_Taxpayer_Non_Taxpayer?="Taxpayer",Unstructured!D17<7),(VLOOKUP(Unstructured!D17,Depreciation_Table,3)),0) -> 17855.548 | E121: =IF(AND(Owner_is_Taxpayer_Non_Taxpayer?="Taxpayer",Unstructured!E17<7),(VLOOKUP(Unstructured!E17,Depreciation_Table,3)),0) -> 28568.877 | F121: =IF(AND(Owner_is_Taxpayer_Non_Taxpayer?="Taxpayer",Unstructured!F17<7),(VLOOKUP(Unstructured!F17,Depreciation_Table,3)),0) -> 17141.326 | G121: =IF(AND(Owner_is_Taxpayer_Non_Taxpayer?="Taxpayer",Unstructured!G17<7),(VLOOKUP(Unstructured!G17,Depreciation_Table,3)),0) -> 10284.796 | H121: =IF(AND(Owner_is_Taxpayer_Non_Taxpayer?="Taxpayer",Unstructured!H17<7),(VLOOKUP(Unstructured!H17,Depreciation_Table,3)),0) -> 10284.796 | I121: =IF(AND(Owner_is_Taxpayer_Non_Taxpayer?="Taxpayer",Unstructured!I17<7),(VLOOKUP(Unstructured!I17,Depreciation_Table,3)),0) -> 5142.3978 | J121: =IF(AND(Owner_is_Taxpayer_Non_Taxpayer?="Taxpayer",Unstructured!J17<7),(VLOOKUP(Unstructured!J17,Depreciation_Table,3)),0) -> 0 | K121: =IF(AND(Owner_is_Taxpayer_Non_Taxpayer?="Taxpayer",Unstructured!K17<7),(VLOOKUP(Unstructured!K17,Depreciation_Table,3)),0) -> 0 | ... AB121: =IF(AND(Owner_is_Taxpayer_Non_Taxpayer?="Taxpayer",Unstructured!AB17<7),(VLOOKUP(Unstructured!AB17,Depreciation_Table,3)),0) -> 0
B122: Start Fed. Carryforward Balance | D122: =IF(Tax_Efficient_Status?="Not Efficient",C124,0) -> 0 | E122: =IF(Tax_Efficient_Status?="Not Efficient",D124,0) -> 0 | F122: =IF(Tax_Efficient_Status?="Not Efficient",E124,0) -> 0 | G122: =IF(Tax_Efficient_Status?="Not Efficient",F124,0) -> 0 | H122: =IF(Tax_Efficient_Status?="Not Efficient",G124,0) -> 0 | I122: =IF(Tax_Efficient_Status?="Not Efficient",H124,0) -> 0 | J122: =IF(Tax_Efficient_Status?="Not Efficient",I124,0) -> 0 | K122: =IF(Tax_Efficient_Status?="Not Efficient",J124,0) -> 0 | ... AB122: =IF(Tax_Efficient_Status?="Not Efficient",AA124,0) -> 0
B123: Federal Taxable Income | D123: =IF(D120>(D121+D122),D120-(D121+D122),0) -> 0 | E123: =IF(E120>(E121+E122),E120-(E121+E122),0) -> 0 | F123: =IF(F120>(F121+F122),F120-(F121+F122),0) -> 0 | G123: =IF(G120>(G121+G122),G120-(G121+G122),0) -> 0 | H123: =IF(H120>(H121+H122),H120-(H121+H122),0) -> 0 | I123: =IF(I120>(I121+I122),I120-(I121+I122),0) -> 131.71099 | J123: =IF(J120>(J121+J122),J120-(J121+J122),0) -> 5247.6186 | K123: =IF(K120>(K121+K122),K120-(K121+K122),0) -> 5351.7131 | ... AB123: =IF(AB120>(AB121+AB122),AB120-(AB121+AB122),0) -> 7473.2911
B124: Excess Current Year Fed.Dep. | D124: =IF(D120>(D121+D122),0,(D121+D122)-D120) -> 13071.734 | E124: =IF(E120>(E121+E122),0,(E121+E122)-E120) -> 23690.169 | F124: =IF(F120>(F121+F122),0,(F121+F122)-F120) -> 12165.841 | G124: =IF(G120>(G121+G122),0,(G121+G122)-G120) -> 5210.6145 | H124: =IF(H120>(H121+H122),0,(H121+H122)-H120) -> 5109.9603 | I124: =IF(I120>(I121+I122),0,(I121+I122)-I120) -> 0 | J124: =IF(J120>(J121+J122),0,(J121+J122)-J120) -> 0 | K124: =IF(K120>(K121+K122),0,(K121+K122)-K120) -> 0 | ... AB124: =IF(AB120>(AB121+AB122),0,(AB121+AB122)-AB120) -> 0
B130: UNSTRUCTURED CHART DATA
C132: Debt Equity Ratio
C133: Equity | D133: =Dashboard!H24 -> 114975.09
C134: Debt | D134: =IF(Dashboard!H27="Yes",Dashboard!H30,0) -> 0
C136: Investor Return Profile
...

Sheet Partnership Flip
H2: Demo Solar PV Model v2.1 | J2: PROPRIETARY AND CONFIDENTIAL
H3: Partnership Flip Model
N4: Cautionary Note
H5: Copyright, 2020 & 2022; All rights reserved by CapIron, Inc. This model may not be sold, licensed or distributed without the prior written approval of CapIron, Inc. DOE Solar District Cup Competitors may use this model for the competition and personal use only. | N5: This model is provided for illustration purposes only. Before using to evaluate any project, it should be audited to ensure functionality and accuracy, and to adapt the model to meet the specific requirements of applicable political and utility authorities, as well as any prospective customer, developer, EPC Contractor, investor, purchaser or lender. This model should not be used as tax advice. You should consult an accounting professional to determine if your specific circumstances allow you to be eligible for all of the credits/benefits demonstrated.
H8: Last Change
H9: Last Change Date
B13: SUPPORTING DATA AND CALCULATIONS
B14: Simplified Partnership Flip | E14: Operating Note: Should not be run with Project-Level Debt of any kind. Set Dashboard cell H27 to "No" prior to running this worksheet. | H14: =IF(Dashboard!H27="Yes", "WARNING: Project Level Debt is turned ON.", "Project Level Debt is turned off in Dashboard Cell H27.") -> Project Level Debt is turned off in Dashboard Cell H27.
B15: (Year End Flip)
B18: Available Cash and Tax Benefits
B19: Year | C19: 0 | D19: 1 | E19: 2 | F19: 3 | G19: 4 | H19: 5 | I19: 6 | J19: 7 | K19: 8 | L19: 9 | M19: 10 | N19: 11 | O19: 12 | P19: 13 | Q19: 14 | R19: 15 | S19: 16 | T19: 17 | U19: 18 | V19: 19 | W19: 20 | X19: 21 | Y19: 22 | Z19: 23 | AA19: 24 | AB19: 25
B20: Cash
B21: Net Income | D21: =Unstructured!D62 -> -13071.734 | E21: =Unstructured!E62 -> -23690.169 | F21: =Unstructured!F62 -> -12165.841 | G21: =Unstructured!G62 -> -5210.6145 | H21: =Unstructured!H62 -> -5109.9603 | I21: =Unstructured!I62 -> 104.05168 | J21: =Unstructured!J62 -> 4145.6187 | K21: =Unstructured!K62 -> 4227.8533 | ... AB21: =Unstructured!AB62 -> 5903.9
B22: Depreciation | D22: =Unstructured!D46 -> 17855.548 | E22: =Unstructured!E46 -> 28568.877 | F22: =Unstructured!F46 -> 17141.326 | G22: =Unstructured!G46 -> 10284.796 | H22: =Unstructured!H46 -> 10284.796 | I22: =Unstructured!I46 -> 5142.3978 | J22: =Unstructured!J46 -> 0 | K22: =Unstructured!K46 -> 0 | ... AB22: =Unstructured!AB46 -> 0
B23: Termination Payment (Year 25) | AB23: =Unstructured!AB80-Unstructured!AB62 -> 17246.264
B24: Total Available Cash | C24: =Unstructured!C80 -> -114975.09 | D24: =SUM(D21:D23) -> 4783.8136 | E24: =SUM(E21:E23) -> 4878.7079 | F24: =SUM(F21:F23) -> 4975.4846 | G24: =SUM(G21:G23) -> 5074.181 | H24: =SUM(H21:H23) -> 5174.8352 | I24: =SUM(I21:I23) -> 5246.4495 | J24: =SUM(J21:J23) -> 4145.6187 | K24: =SUM(K21:K23) -> 4227.8533 | ... AB24: =SUM(AB21:AB23) -> 23150.163
B26: After-Tax Excess Tax Benefits
B27: State Tax Credit | D27: =Unstructured!D71 -> 0
B28: State Depreciation | D28: =Unstructured!D72 -> 258.16675 | E28: =Unstructured!E72 -> 467.88083 | F28: =Unstructured!F72 -> 240.27536 | G28: =Unstructured!G72 -> 102.90964 | H28: =Unstructured!H72 -> 100.92172 | I28: =Unstructured!I72 -> 0 | J28: =Unstructured!J72 -> 0 | K28: =Unstructured!K72 -> 0 | ... AB28: =Unstructured!AB72 -> 0
B29: Federal Depreciation | D29: =Unstructured!D70 -> 2745.0642 | E29: =Unstructured!E70 -> 4974.9354 | F29: =Unstructured!F70 -> 2554.8267 | G29: =Unstructured!G70 -> 1094.229 | H29: =Unstructured!H70 -> 1073.0917 | I29: =Unstructured!I70 -> 0 | J29: =Unstructured!J70 -> 0 | K29: =Unstructured!K70 -> 0 | ... AB29: =Unstructured!AB70 -> 0
B30: ITC | D30: =Unstructured!D69 -> 31509.79
B31: Total Excess Tax Benefit | D31: =SUM(D27:D30) -> 34513.021 | E31: =SUM(E27:E30) -> 5442.8162 | F31: =SUM(F27:F30) -> 2795.102 | G31: =SUM(G27:G30) -> 1197.1387 | H31: =SUM(H27:H30) -> 1174.0134 | I31: =SUM(I27:I30) -> 0 | J31: =SUM(J27:J30) -> 0 | K31: =SUM(K27:K30) -> 0 | ... AB31: =SUM(AB27:AB30) -> 0
B34: Cash Distributions - Waterfall
B35: Year | C35: 0 | D35: 1 | E35: 2 | F35: 3 | G35: 4 | H35: 5 | I35: 6 | J35: 7 | K35: 8 | L35: 9 | M35: 10 | N35: 11 | O35: 12 | P35: 13 | Q35: 14 | R35: 15 | S35: 16 | T35: 17 | U35: 18 | V35: 19 | W35: 20 | X35: 21 | Y35: 22 | Z35: 23 | AA35: 24 | AB35: 25
B36: Available Cash for Distr. | D36: =D24 -> 4783.8136 | E36: =E24 -> 4878.7079 | F36: =F24 -> 4975.4846 | G36: =G24 -> 5074.181 | H36: =H24 -> 5174.8352 | I36: =I24 -> 5246.4495 | J36: =J24 -> 4145.6187 | K36: =K24 -> 4227.8533 | ... AB36: =AB24 -> 23150.163
B37: 1. Tax Investor, Cash-on-Cash Return | D37: =IF(D35>Time_Based_Flip_Target_Year,0,(Cash_on_Cash_Return_Premium*Tax_Equity_Investment_Share*Equity_Investment)) -> 1812.4673 | E37: =IF(E35>Time_Based_Flip_Target_Year,0,(Cash_on_Cash_Return_Premium*Tax_Equity_Investment_Share*Equity_Investment)) -> 1812.4673 | F37: =IF(F35>Time_Based_Flip_Target_Year,0,(Cash_on_Cash_Return_Premium*Tax_Equity_Investment_Share*Equity_Investment)) -> 1812.4673 | G37: =IF(G35>Time_Based_Flip_Target_Year,0,(Cash_on_Cash_Return_Premium*Tax_Equity_Investment_Share*Equity_Investment)) -> 1812.4673 | H37: =IF(H35>Time_Based_Flip_Target_Year,0,(Cash_on_Cash_Return_Premium*Tax_Equity_Investment_Share*Equity_Investment)) -> 1812.4673 | I37: =IF(I35>Time_Based_Flip_Target_Year,0,(Cash_on_Cash_Return_Premium*Tax_Equity_Investment_Share*Equity_Investment)) -> 0 | J37: =IF(J35>Time_Based_Flip_Target_Year,0,(Cash_on_Cash_Return_Premium*Tax_Equity_Investment_Share*Equity_Investment)) -> 0 | K37: =IF(K35>Time_Based_Flip_Target_Year,0,(Cash_on_Cash_Return_Premium*Tax_Equity_Investment_Share*Equity_Investment)) -> 0 | ... AB37: =IF(AB35>Time_Based_Flip_Target_Year,0,(Cash_on_Cash_Return_Premium*Tax_Equity_Investment_Share*Equity_Investment)) -> 0
B38: Net Remaining Cash | D38: =D36-D37 -> 2971.3462 | E38: =E36-E37 -> 3066.2406 | F38: =F36-F37 -> 3163.0173 | G38: =G36-G37 -> 3261.7137 | H38: =H36-H37 -> 3362.3679 | I38: =I36-I37 -> 5246.4495 | J38: =J36-J37 -> 4145.6187 | K38: =K36-K37 -> 4227.8533 | ... AB38: =AB36-AB37 -> 23150.163
B40: 2. Developer/Sponsor Incentive Fee | D40: =IF(D35>Time_Based_Flip_Target_Year,0,Mgt._Fee__Share__of_Remaining_Cash_Flow*D38) -> 2674.2116 | E40: =IF(E35>Time_Based_Flip_Target_Year,0,Mgt._Fee__Share__of_Remaining_Cash_Flow*E38) -> 2759.6166 | F40: =IF(F35>Time_Based_Flip_Target_Year,0,Mgt._Fee__Share__of_Remaining_Cash_Flow*F38) -> 2846.7156 | G40: =IF(G35>Time_Based_Flip_Target_Year,0,Mgt._Fee__Share__of_Remaining_Cash_Flow*G38) -> 2935.5424 | H40: =IF(H35>Time_Based_Flip_Target_Year,0,Mgt._Fee__Share__of_Remaining_Cash_Flow*H38) -> 3026.1311 | I40: =IF(I35>Time_Based_Flip_Target_Year,0,Mgt._Fee__Share__of_Remaining_Cash_Flow*I38) -> 0 | J40: =IF(J35>Time_Based_Flip_Target_Year,0,Mgt._Fee__Share__of_Remaining_Cash_Flow*J38) -> 0 | K40: =IF(K35>Time_Based_Flip_Target_Year,0,Mgt._Fee__Share__of_Remaining_Cash_Flow*K38) -> 0 | ... AB40: =IF(AB35>Time_Based_Flip_Target_Year,0,Mgt._Fee__Share__of_Remaining_Cash_Flow*AB38) -> 0
B41: Net Remaining Cash | D41: =D38-D40 -> 297.13462 | E41: =E38-E40 -> 306.62406 | F41: =F38-F40 -> 316.30173 | G41: =G38-G40 -> 326.17137 | H41: =H38-H40 -> 336.23679 | I41: =I38-I40 -> 5246.4495 | J41: =J38-J40 -> 4145.6187 | K41: =K38-K40 -> 4227.8533 | ... AB41: =AB38-AB40 -> 23150.163
B43: 3. Remaining Balance | D43: =D41 -> 297.13462 | E43: =E41 -> 306.62406 | F43: =F41 -> 316.30173 | G43: =G41 -> 326.17137 | H43: =H41 -> 336.23679 | I43: =I41 -> 5246.4495 | J43: =J41 -> 4145.6187 | K43: =K41 -> 4227.8533 | ... AB43: =AB41 -> 23150.163
B44: Tax Equity Investor | D44: =D43*IF(D35>Time_Based_Flip_Target_Year,Tax_Equity_Post_Flip_Share,Tax_Equity_Pre_Flip_Share) -> 294.16328 | E44: =E43*IF(E35>Time_Based_Flip_Target_Year,Tax_Equity_Post_Flip_Share,Tax_Equity_Pre_Flip_Share) -> 303.55782 | F44: =F43*IF(F35>Time_Based_Flip_Target_Year,Tax_Equity_Post_Flip_Share,Tax_Equity_Pre_Flip_Share) -> 313.13872 | G44: =G43*IF(G35>Time_Based_Flip_Target_Year,Tax_Equity_Post_Flip_Share,Tax_Equity_Pre_Flip_Share) -> 322.90966 | H44: =H43*IF(H35>Time_Based_Flip_Target_Year,Tax_Equity_Post_Flip_Share,Tax_Equity_Pre_Flip_Share) -> 332.87442 | I44: =I43*IF(I35>Time_Based_Flip_Target_Year,Tax_Equity_Post_Flip_Share,Tax_Equity_Pre_Flip_Share) -> 262.32247 | J44: =J43*IF(J35>Time_Based_Flip_Target_Year,Tax_Equity_Post_Flip_Share,Tax_Equity_Pre_Flip_Share) -> 207.28093 | K44: =K43*IF(K35>Time_Based_Flip_Target_Year,Tax_Equity_Post_Flip_Share,Tax_Equity_Pre_Flip_Share) -> 211.39267 | ... AB44: =AB43*IF(AB35>Time_Based_Flip_Target_Year,Tax_Equity_Post_Flip_Share,Tax_Equity_Pre_Flip_Share) -> 1157.5082
B45: Cash Equity/Sponsor | D45: =D43-D44 -> 2.9713462 | E45: =E43-E44 -> 3.0662406 | F45: =F43-F44 -> 3.1630173 | G45: =G43-G44 -> 3.2617137 | H45: =H43-H44 -> 3.3623679 | I45: =I43-I44 -> 4984.127 | J45: =J43-J44 -> 3938.3378 | K45: =K43-K44 -> 4016.4607 | ... AB45: =AB43-AB44 -> 21992.655
B47: Aggregate Cash Distributions
B48: Tax Equity Investor | D48: =SUM(D37,D44) -> 2106.6306 | E48: =SUM(E37,E44) -> 2116.0251 | F48: =SUM(F37,F44) -> 2125.606 | G48: =SUM(G37,G44) -> 2135.377 | H48: =SUM(H37,H44) -> 2145.3417 | I48: =SUM(I37,I44) -> 262.32247 | J48: =SUM(J37,J44) -> 207.28093 | K48: =SUM(K37,K44) -> 211.39267 | ... AB48: =SUM(AB37,AB44) -> 1157.5082
B49: Developer/Sponsor | D49: =SUM(D40,D45) -> 2677.183 | E49: =SUM(E40,E45) -> 2762.6828 | F49: =SUM(F40,F45) -> 2849.8786 | G49: =SUM(G40,G45) -> 2938.8041 | H49: =SUM(H40,H45) -> 3029.4935 | I49: =SUM(I40,I45) -> 4984.127 | J49: =SUM(J40,J45) -> 3938.3378 | K49: =SUM(K40,K45) -> 4016.4607 | ... AB49: =SUM(AB40,AB45) -> 21992.655
B50: Aggregate Cash Distribution | D50: =D48+D49 -> 4783.8136 | E50: =E48+E49 -> 4878.7079 | F50: =F48+F49 -> 4975.4846 | G50: =G48+G49 -> 5074.181 | H50: =H48+H49 -> 5174.8352 | I50: =I48+I49 -> 5246.4495 | J50: =J48+J49 -> 4145.6187 | K50: =K48+K49 -> 4227.8533 | ... AB50: =AB48+AB49 -> 23150.163
B53: Simplified Partnership Flip
B54: Year | C54: 0 | D54: 1 | E54: 2 | F54: 3 | G54: 4 | H54: 5 | I54: 6 | J54: 7 | K54: 8 | L54: 9 | M54: 10 | N54: 11 | O54: 12 | P54: 13 | Q54: 14 | R54: 15 | S54: 16 | T54: 17 | U54: 18 | V54: 19 | W54: 20 | X54: 21 | Y54: 22 | Z54: 23 | AA54: 24 | AB54: 25
B55: Tax Equity Partner
B56: Cash Only Benefits | C56: =-Tax_Equity_Investment_Share*Project_Sale_Price -> -51784.781 | D56: =D48 -> 2106.6306 | E56: =E48 -> 2116.0251 | F56: =F48 -> 2125.606 | G56: =G48 -> 2135.377 | H56: =H48 -> 2145.3417 | I56: =I48 -> 262.32247 | J56: =J48 -> 207.28093 | K56: =K48 -> 211.39267 | ... AB56: =AB48 -> 1157.5082
B57: Excess Tax Only Benefits | D57: =IF(D54>Time_Based_Flip_Target_Year,Tax_Equity_Post_Flip_Share,Tax_Equity_Pre_Flip_Share)*D31 -> 34167.891 | E57: =IF(E54>Time_Based_Flip_Target_Year,Tax_Equity_Post_Flip_Share,Tax_Equity_Pre_Flip_Share)*E31 -> 5388.3881 | F57: =IF(F54>Time_Based_Flip_Target_Year,Tax_Equity_Post_Flip_Share,Tax_Equity_Pre_Flip_Share)*F31 -> 2767.151 | G57: =IF(G54>Time_Based_Flip_Target_Year,Tax_Equity_Post_Flip_Share,Tax_Equity_Pre_Flip_Share)*G31 -> 1185.1673 | H57: =IF(H54>Time_Based_Flip_Target_Year,Tax_Equity_Post_Flip_Share,Tax_Equity_Pre_Flip_Share)*H31 -> 1162.2733 | I57: =IF(I54>Time_Based_Flip_Target_Year,Tax_Equity_Post_Flip_Share,Tax_Equity_Pre_Flip_Share)*I31 -> 0 | J57: =IF(J54>Time_Based_Flip_Target_Year,Tax_Equity_Post_Flip_Share,Tax_Equity_Pre_Flip_Share)*J31 -> 0 | K57: =IF(K54>Time_Based_Flip_Target_Year,Tax_Equity_Post_Flip_Share,Tax_Equity_Pre_Flip_Share)*K31 -> 0 | ... AB57: =IF(AB54>Time_Based_Flip_Target_Year,Tax_Equity_Post_Flip_Share,Tax_Equity_Pre_Flip_Share)*AB31 -> 0
B58: Cash & Tax Benefits | C58: =C56 -> -51784.781 | D58: =D56+D57 -> 36274.522 | E58: =E56+E57 -> 7504.4132 | F58: =F56+F57 -> 4892.757 | G58: =G56+G57 -> 3320.5443 | H58: =H56+H57 -> 3307.615 | I58: =I56+I57 -> 262.32247 | J58: =J56+J57 -> 207.28093 | K58: =K56+K57 -> 211.39267 | ... AB58: =AB56+AB57 -> 1157.5082
B59: Cash & Tax IRR | C59: 0 | D59: =IFERROR(IRR($C58:D$58),0) -> -0.29951385 | E59: =IFERROR(IRR($C58:E$58),0) -> -0.13247013 | F59: =IFERROR(IRR($C58:F$58),0) -> -0.044399169 | G59: =IFERROR(IRR($C58:G$58),0) -> 0.0026284793 | H59: =IFERROR(IRR($C58:H$58),0) -> 0.039275539 | I59: =IFERROR(IRR($C58:I$58),0) -> 0.041740278 | J59: =IFERROR(IRR($C58:J$58),0) -> 0.043574183 | K59: =IFERROR(IRR($C58:K$58),0) -> 0.045331555 | ... AB59: =IFERROR(IRR($C58:AB$58),0) -> 0.065573809
B60: Cum. Cash & Tax Flows | C60: =C58 -> -51784.781 | D60: =C60+D58 -> -15510.259 | E60: =D60+E58 -> -8005.8457 | F60: =E60+F58 -> -3113.0887 | G60: =F60+G58 -> 207.45557 | H60: =G60+H58 -> 3515.0706 | I60: =H60+I58 -> 3777.393 | J60: =I60+J58 -> 3984.674 | K60: =J60+K58 -> 4196.0666 | ... AB60: =AA60+AB58 -> 9366.8446
B61: NPV of Cash & Tax Flows | C61: =NPV(Investor_Discount_Rate,D58:AB58)+C58 -> 60.946624
B62: IRR of Cash & Tax Flows | C62: =IRR(C58:AB58) -> 0.065573809
B63: Cash-on-Cash NPV | C63: =NPV(Investor_Discount_Rate,D56:AB56)+C58 -> -40832.665
B64: Cash-on-Cash IRR | C64: =IRR(C56:AB56) -> -0.092670539
B65: 1st Year, Post Flip | C65: =Time_Based_Flip_Target_Year+1 -> 6
B66: IRR at Time of Flip | C66: =INDEX(C54:AB59,6,MATCH(C65,C35:AB35,0)) -> 0.041740278
B68: Developer/Sponsor (Cash Equity)
B69: Cash Only Benefits | C69: =-(Project_Sale_Price*Cash_Equity_Investment_Share) -> -63190.309 | D69: =D49 -> 2677.183 | E69: =E49 -> 2762.6828 | F69: =F49 -> 2849.8786 | G69: =G49 -> 2938.8041 | H69: =H49 -> 3029.4935 | I69: =I49 -> 4984.127 | J69: =J49 -> 3938.3378 | K69: =K49 -> 4016.4607 | ... AB69: =AB49 -> 21992.655
B70: Excess Tax Only Benefits | D70: =D31-D57 -> 345.13021 | E70: =E31-E57 -> 54.428162 | F70: =F31-F57 -> 27.95102 | G70: =G31-G57 -> 11.971387 | H70: =H31-H57 -> 11.740134 | I70: =I31-I57 -> 0 | J70: =J31-J57 -> 0 | K70: =K31-K57 -> 0 | ... AB70: =AB31-AB57 -> 0
B71: Cash & Tax Benefits | C71: =C69 -> -63190.309 | D71: =D69+D70 -> 3022.3132 | E71: =E69+E70 -> 2817.111 | F71: =F69+F70 -> 2877.8296 | G71: =G69+G70 -> 2950.7755 | H71: =H69+H70 -> 3041.2336 | I71: =I69+I70 -> 4984.127 | J71: =J69+J70 -> 3938.3378 | K71: =K69+K70 -> 4016.4607 | ... AB71: =AB69+AB70 -> 21992.655
B72: Cash & Tax IRR | C72: 0 | D72: =IFERROR(IRR($C71:D$71),0) -> -0.95217126 | E72: =IFERROR(IRR($C71:E$71),0) -> -0.76359263 | F72: =IFERROR(IRR($C71:F$71),0) -> -0.58314215 | G72: =IFERROR(IRR($C71:G$71),0) -> -0.44684351 | H72: =IFERROR(IRR($C71:H$71),0) -> -0.34639623 | I72: =IFERROR(IRR($C71:I$71),0) -> -0.24284884 | J72: =IFERROR(IRR($C71:J$71),0) -> -0.18827426 | K72: =IFERROR(IRR($C71:K$71),0) -> -0.14598246 | ... AB72: =IFERROR(IRR($C71:AB$71),0) -> 0.049390537
B73: Cum. Cash & Tax Flows | C73: =C71 -> -63190.309 | D73: =C73+D71 -> -60167.996 | E73: =D73+E71 -> -57350.885 | F73: =E73+F71 -> -54473.056 | G73: =F73+G71 -> -51522.28 | H73: =G73+H71 -> -48481.047 | I73: =H73+I71 -> -43496.92 | J73: =I73+J71 -> -39558.582 | K73: =J73+K71 -> -35542.121 | ... AB73: =AA73+AB71 -> 62702.659
B74: NPV of Cash & Tax Flows | C74: =NPV(Investor_Discount_Rate,D71:AB71)+C71 -> -10635.056
B75: IRR of Cash & Tax Flows | C75: =IRR(C71:AB71) -> 0.049390537
B76: Cash-on-cash NPV | C76: =NPV(Investor_Discount_Rate,D69:AB69)+C71 -> -11048.123
B77: Cash-on-Cash IRR | C77: =IRR(C69:AB69) -> 0.048850122
B83: Simplified Partnership Flip Chart Data
B86: Cumulative Returns (Cash & Tax)
B87: Year | C87: 0 | D87: 1 | E87: 2 | F87: 3 | G87: 4 | H87: 5 | I87: 6 | J87: 7 | K87: 8 | L87: 9 | M87: 10 | N87: 11 | O87: 12 | P87: 13 | Q87: 14 | R87: 15 | S87: 16 | T87: 17 | U87: 18 | V87: 19 | W87: 20 | X87: 21 | Y87: 22 | Z87: 23 | AA87: 24 | AB87: 25
B88: Tax Equity Partner | C88: =C60 -> -51784.781 | D88: =D60 -> -15510.259 | E88: =E60 -> -8005.8457 | F88: =F60 -> -3113.0887 | G88: =G60 -> 207.45557 | H88: =H60 -> 3515.0706 | I88: =I60 -> 3777.393 | J88: =J60 -> 3984.674 | ... AB88: =AB60 -> 9366.8446
B89: Developer/Sponsor | C89: =C73 -> -63190.309 | D89: =D73 -> -60167.996 | E89: =E73 -> -57350.885 | F89: =F73 -> -54473.056 | G89: =G73 -> -51522.28 | H89: =H73 -> -48481.047 | I89: =I73 -> -43496.92 | J89: =J73 -> -39558.582 | ... AB89: =AB73 -> 62702.659
B91: Equity Contributions
B92: Tax Equity Partner | C92: =-C56 -> 51784.781
B93: Developer/Sponsor | C93: =-C69 -> 63190.309
B95: Cumulative Returns (Cash & Tax)
B96: Year | C96: 0 | D96: 1 | E96: 2 | F96: 3 | G96: 4 | H96: 5 | I96: 6 | J96: 7 | K96: 8 | L96: 9 | M96: 10 | N96: 11 | O96: 12 | P96: 13 | Q96: 14 | R96: 15 | S96: 16 | T96: 17 | U96: 18 | V96: 19 | W96: 20 | X96: 21 | Y96: 22 | Z96: 23 | AA96: 24 | AB96: 25
B97: Tax Equity Partner | C97: =C58 -> -51784.781 | D97: =D58 -> 36274.522 | E97: =E58 -> 7504.4132 | F97: =F58 -> 4892.757 | G97: =G58 -> 3320.5443 | H97: =H58 -> 3307.615 | I97: =I58 -> 262.32247 | J97: =J58 -> 207.28093 | ... AB97: =AB58 -> 1157.5082
B98: Developer/Sponsor | C98: =C71 -> -63190.309 | D98: =D71 -> 3022.3132 | E98: =E71 -> 2817.111 | F98: =F71 -> 2877.8296 | G98: =G71 -> 2950.7755 | H98: =H71 -> 3041.2336 | I98: =I71 -> 4984.127 | J98: =J71 -> 3938.3378 | ... AB98: =AB71 -> 21992.655

Sheet Customer Analysis
I2: Demo Solar PV Model v2.1 | O2: PROPRIETARY AND CONFIDENTIAL
I3: Customer Analysis
O4: Cautionary Note
I5: Copyright, 2020 & 2022; All rights reserved by CapIron, Inc. This model may not be sold, licensed or distributed without the prior written approval of CapIron, Inc. DOE Solar District Cup Competitors may use this model for the competition and personal use only. | O5: This model is provided for illustration purposes only. Before using to evaluate any project, it should be audited to ensure functionality and accuracy, and to adapt the model to meet the specific requirements of applicable political and utility authorities, as well as any prospective customer, developer, EPC Contractor, investor, purchaser or lender. This model should not be used as tax advice. You should consult an accounting professional to determine if your specific circumstances allow you to be eligible for all of the credits/benefits demonstrated.
I8: Last Change
I9: Last Change Date
B13: SUPPORTING DATA AND CALCULATIONS
B14: Customer Analysis
B16: PPA Customer Analysis
B17: Year | C17: 0 | D17: 1 | E17: 2 | F17: 3 | G17: 4 | H17: 5 | I17: 6 | J17: 7 | K17: 8 | L17: 9 | M17: 10 | N17: 11 | O17: 12 | P17: 13 | Q17: 14 | R17: 15 | S17: 16 | T17: 17 | U17: 18 | V17: 19 | W17: 20 | X17: 21 | Y17: 22 | Z17: 23 | AA17: 24 | AB17: 25
B18: Annual Utility Purchases, without PPA | D18: =Customer_Monthly_kWh_Usage*12 -> 3952823 | E18: =D18 -> 3952823 | F18: =E18 -> 3952823 | G18: =F18 -> 3952823 | H18: =G18 -> 3952823 | I18: =H18 -> 3952823 | J18: =I18 -> 3952823 | K18: =J18 -> 3952823 | L18: =K18 -> 3952823 | ... AB18: =AA18 -> 3952823
B19: Annual Utility Purchases, with PPA | D19: =D18-D21 -> 3860724.9 | E19: =E18-E21 -> 3861185.4 | F19: =F18-F21 -> 3861643.6 | G19: =G18-G21 -> 3862099.5 | H19: =H18-H21 -> 3862553.1 | I19: =I18-I21 -> 3863004.5 | J19: =J18-J21 -> 3863453.6 | K19: =K18-K21 -> 3863900.4 | ... AB19: =AB18-AB21 -> 3871163.9
B21: P50 Production (kWh) | D21: =Unstructured!D21 -> 92098.11 | E21: =Unstructured!E21 -> 91637.619 | F21: =Unstructured!F21 -> 91179.431 | G21: =Unstructured!G21 -> 90723.534 | H21: =Unstructured!H21 -> 90269.917 | I21: =Unstructured!I21 -> 89818.567 | J21: =Unstructured!J21 -> 89369.474 | K21: =Unstructured!K21 -> 88922.627 | ... AB21: =Unstructured!AB21 -> 81659.113
B22: Utility Price per kWh | D22: =Customer_Utility_Charge_kWh -> 0.073648296 | E22: =D22*(1+Customer_Utility_Charge_Escalator) -> 0.075489503 | F22: =E22*(1+Customer_Utility_Charge_Escalator) -> 0.077376741 | G22: =F22*(1+Customer_Utility_Charge_Escalator) -> 0.07931116 | H22: =G22*(1+Customer_Utility_Charge_Escalator) -> 0.081293939 | I22: =H22*(1+Customer_Utility_Charge_Escalator) -> 0.083326287 | J22: =I22*(1+Customer_Utility_Charge_Escalator) -> 0.085409444 | K22: =J22*(1+Customer_Utility_Charge_Escalator) -> 0.08754468 | L22: =K22*(1+Customer_Utility_Charge_Escalator) -> 0.089733297 | ... AB22: =AA22*(1+Customer_Utility_Charge_Escalator) -> 0.13320958
B23: Utility Demand Charge | D23: =D22*Customer_Dem_Charge_Percent -> 0 | E23: =E22*Customer_Dem_Charge_Percent -> 0 | F23: =F22*Customer_Dem_Charge_Percent -> 0 | G23: =G22*Customer_Dem_Charge_Percent -> 0 | H23: =H22*Customer_Dem_Charge_Percent -> 0 | I23: =I22*Customer_Dem_Charge_Percent -> 0 | J23: =J22*Customer_Dem_Charge_Percent -> 0 | K23: =K22*Customer_Dem_Charge_Percent -> 0 | ... AB23: =AB22*Customer_Dem_Charge_Percent -> 0
B24: PPA Price per kWh | D24: =Unstructured!D19 -> 0.07303158 | E24: =Unstructured!E19 -> 0.07485737 | F24: =Unstructured!F19 -> 0.076728804 | G24: =Unstructured!G19 -> 0.078647024 | H24: =Unstructured!H19 -> 0.0806132 | I24: =Unstructured!I19 -> 0.08262853 | J24: =Unstructured!J19 -> 0.084694243 | K24: =Unstructured!K19 -> 0.086811599 | ... AB24: =Unstructured!AB19 -> 0.13209411
B25: Displaced Utility Cost | D25: =D21*(D22+D23) -> 6782.8689 | E25: =E21*(E22+E23) -> 6917.6784 | F25: =F21*(F22+F23) -> 7055.1672 | G25: =G21*(G22+G23) -> 7195.3887 | H25: =H21*(H22+H23) -> 7338.397 | I25: =I21*(I22+I23) -> 7484.2477 | J25: =J21*(J22+J23) -> 7632.9971 | K25: =K21*(K22+K23) -> 7784.7029 | ... AB25: =AB21*(AB22+AB23) -> 10877.776
B26: PPA Cost | D26: =D21*D24 -> 6726.0705 | E26: =E21*E24 -> 6859.7512 | F26: =F21*F24 -> 6996.0887 | G26: =G21*G24 -> 7135.136 | H26: =H21*H24 -> 7276.9468 | I26: =I21*I24 -> 7421.5761 | J26: =J21*J24 -> 7569.0799 | K26: =K21*K24 -> 7719.5154 | ... AB26: =AB21*AB24 -> 10786.688
B27: Customer Net Savings | D27: =D25-D26 -> 56.798364 | E27: =E25-E26 -> 57.927232 | F27: =F25-F26 -> 59.078536 | G27: =G25-G26 -> 60.252722 | H27: =H25-H26 -> 61.450244 | I27: =I25-I26 -> 62.671568 | J27: =J25-J26 -> 63.917165 | K27: =K25-K26 -> 65.187519 | ... AB27: =AB25-AB26 -> 91.088288
B28: NPV of Customer Net Savings (25-Year Term) | D28: =NPV(Customer_Discount_Rate,D27:AB27) -> 876.08977
B30: Buyout Price Calculation
B31: NPV of remaining pmts + terminal value (Yr. 20) | J31: =NPV(Customer_Discount_Rate,Unstructured!K87:$AB$87) -> 58787.204 | K31: =NPV(Customer_Discount_Rate,Unstructured!L87:$AB$87) -> 58086.583 | L31: =NPV(Customer_Discount_Rate,Unstructured!M87:$AB$87) -> 57260.059 | M31: =NPV(Customer_Discount_Rate,Unstructured!N87:$AB$87) -> 56298.414 | N31: =NPV(Customer_Discount_Rate,Unstructured!O87:$AB$87) -> 55191.844 | O31: =NPV(Customer_Discount_Rate,Unstructured!P87:$AB$87) -> 53929.924 | P31: =NPV(Customer_Discount_Rate,Unstructured!Q87:$AB$87) -> 52501.568 | Q31: =NPV(Customer_Discount_Rate,Unstructured!R87:$AB$87) -> 50894.99 | ... AA31: =NPV(Customer_Discount_Rate,Unstructured!AB87:$AB$87) -> 21839.777 | AB31: =NPV(Customer_Discount_Rate,Unstructured!$AB87:AC$87) -> 21839.777
B32: Terminal Value for NPV | J32: 0 | K32: 0 | L32: 0 | M32: 0 | N32: 0 | O32: 0 | P32: 0 | Q32: 0 | R32: 0 | S32: 0 | T32: 0 | U32: 0 | V32: 0 | W32: 0 | X32: 0 | Y32: 0 | Z32: 0 | AA32: 0 | AB32: 0
B33: Est. NPV of Terminal Value | J33: =NPV(Customer_Discount_Rate,J32:W32) -> 0 | K33: =NPV(Customer_Discount_Rate,K32:AB32) -> 0 | L33: =NPV(Customer_Discount_Rate,L32:Y32) -> 0 | M33: =NPV(Customer_Discount_Rate,M32:Z32) -> 0 | N33: =NPV(Customer_Discount_Rate,N32:AA32) -> 0 | O33: =NPV(Customer_Discount_Rate,O32:AB32) -> 0 | P33: =NPV(Customer_Discount_Rate,P32:AC32) -> 0 | Q33: =NPV(Customer_Discount_Rate,Q32:AD32) -> 0 | R33: =NPV(Customer_Discount_Rate,R32:AE32) -> 0 | S33: =NPV(Customer_Discount_Rate,S32:AF32) -> 0 | ... AB33: =NPV(Customer_Discount_Rate,AB32:AO32) -> 0
B34: Year-End Buyout Price | J34: =SUM(J31+J33) -> 58787.204 | K34: =SUM(K31+K33) -> 58086.583 | L34: =SUM(L31+L33) -> 57260.059 | M34: =SUM(M31+M33) -> 56298.414 | N34: =SUM(N31+N33) -> 55191.844 | O34: =SUM(O31+O33) -> 53929.924 | P34: =SUM(P31+P33) -> 52501.568 | Q34: =SUM(Q31+Q33) -> 50894.99 | ... AB34: =SUM(AB31+AB33) -> 21839.777
B36: Simple LCOE Analysis (PPA vs. Business-As-Usual)
B37: Utility Purchased Electricity
B38: Total Lifecycle Utility Purchased Electricity (kWh) | D38: =SUM(D21:AB21) -> 2169458.6
B39: Total Utility Price | D39: =SUM(D25:AB25) -> 216910.86
B40: Utility - Simple LCOE | D40: =D39/D38 -> 0.099983867
B42: PPA Purchased Electricity
B43: Total Lifecyle Production (kWh) | D43: =SUM(D21:AB21) -> 2169458.6
B44: Totl PPA Price | D44: =SUM(D26:AB26) -> 215094.49
B45: PPA - Simple LCOE | D45: =D44/D43 -> 0.099146623
B47: Adj. LCOE with Total Costs - Upfront Purchase vs. PPA w/Later Buyout
B49: Purchase Price | C49: =-Unstructured!C80 -> 114975.09
B50: Buyout Price | J50: =J31 -> 58787.204 | K50: =K31 -> 58086.583 | L50: =L31 -> 57260.059 | M50: =M31 -> 56298.414 | N50: =N31 -> 55191.844 | O50: =O31 -> 53929.924 | P50: =P31 -> 52501.568 | Q50: =Q31 -> 50894.99 | ... AB50: =AB31 -> 21839.777
B51: Historical PPA Costs | C51: 0 | D51: 0 | E51: =SUM($D$26:E26) -> 13585.822 | F51: =SUM($D$26:F26) -> 20581.91 | G51: =SUM($D$26:G26) -> 27717.046 | H51: =SUM($D$26:H26) -> 34993.993 | I51: =SUM($D$26:I26) -> 42415.569 | J51: =SUM($D$26:J26) -> 49984.649 | K51: =SUM($D$26:K26) -> 57704.165 | L51: =SUM($D$26:L26) -> 65577.105 | ... AB51: =SUM($D$26:AB26) -> 215094.49
B52: Operating Costs | C52: =NPV(Customer_Discount_Rate,Unstructured!D38:$AB$38) -> 22724.099 | D52: =NPV(Customer_Discount_Rate,Unstructured!E38:$AB$38) -> 22616.113 | E52: =NPV(Customer_Discount_Rate,Unstructured!F38:$AB$38) -> 22472.219 | F52: =NPV(Customer_Discount_Rate,Unstructured!G38:$AB$38) -> 22289.674 | G52: =NPV(Customer_Discount_Rate,Unstructured!H38:$AB$38) -> 22065.559 | H52: =NPV(Customer_Discount_Rate,Unstructured!I38:$AB$38) -> 21796.767 | I52: =NPV(Customer_Discount_Rate,Unstructured!J38:$AB$38) -> 21479.994 | J52: =NPV(Customer_Discount_Rate,Unstructured!K38:$AB$38) -> 21111.722 | ... AA52: =NPV(Customer_Discount_Rate,Unstructured!AB38:$AB$38) -> 2232.7415 | AB52: =NPV(Customer_Discount_Rate,Unstructured!$AB38:AC$38) -> 2232.7415
B53: Total Costs | C53: =SUM(C49:C52) -> 137699.19 | D53: =SUM(D49:D52) -> 22616.113 | E53: =SUM(E49:E52) -> 36058.04 | F53: =SUM(F49:F52) -> 42871.584 | G53: =SUM(G49:G52) -> 49782.605 | H53: =SUM(H49:H52) -> 56790.76 | I53: =SUM(I49:I52) -> 63895.563 | J53: =SUM(J49:J52) -> 129883.58 | ... AB53: =SUM(AB49:AB52) -> 239167.01
C54: Adj. LCOE with total costs
B55: Purchase/Buyout Year
B56: Upfront Purchase | C56: =$C$53/$D$43 -> 0.063471683 | D56: per kWh
B57: Year 7 | C57: =$J$53/$D$43 -> 0.059869119 | D57: per kWh
B58: Year 10 | C58: =$M$53/$D$43 -> 0.06894082 | D58: per kWh
B59: Year 15 | C59: =$R$53/$D$43 -> 0.08348561 | D59: per kWh
B60: Year 20 | C60: =$W$53/$D$43 -> 0.096586251 | D60: per kWh
B61: Year 25 | C61: =$AB$53/$D$43 -> 0.11024272 | D61: per kWh
B64: After-Tax Owner Customer Economics | D64: 1 | E64: Assumes Customer purchases system and can use tax benefits efficiently; also assumes the PPA-price equivalent as the value of kWh generated by the solar system.
B65: Year | C65: 0 | D65: 1 | E65: 2 | F65: 3 | G65: 4 | H65: 5 | I65: 6 | J65: 7 | K65: 8 | L65: 9 | M65: 10 | N65: 11 | O65: 12 | P65: 13 | Q65: 14 | R65: 15 | S65: 16 | T65: 17 | U65: 18 | V65: 19 | W65: 20 | X65: 21 | Y65: 22 | Z65: 23 | AA65: 24 | AB65: 25
B66: Displaced Utility Cost Savings | D66: =D25 -> 6782.8689 | E66: =E25 -> 6917.6784 | F66: =F25 -> 7055.1672 | G66: =G25 -> 7195.3887 | H66: =H25 -> 7338.397 | I66: =I25 -> 7484.2477 | J66: =J25 -> 7632.9971 | K66: =K25 -> 7784.7029 | ... AB66: =AB25 -> 10877.776
B67: After-Tax Value of Cost Savings | D67: =D66*(Taxpayer_Marginal_Rate+IF(Tax_Efficient_Status?="State & Federal",State_Income_Tax_Rate,0)) -> 1593.9742 | E67: =E66*(Taxpayer_Marginal_Rate+IF(Tax_Efficient_Status?="State & Federal",State_Income_Tax_Rate,0)) -> 1625.6544 | F67: =F66*(Taxpayer_Marginal_Rate+IF(Tax_Efficient_Status?="State & Federal",State_Income_Tax_Rate,0)) -> 1657.9643 | G67: =G66*(Taxpayer_Marginal_Rate+IF(Tax_Efficient_Status?="State & Federal",State_Income_Tax_Rate,0)) -> 1690.9163 | H67: =H66*(Taxpayer_Marginal_Rate+IF(Tax_Efficient_Status?="State & Federal",State_Income_Tax_Rate,0)) -> 1724.5233 | I67: =I66*(Taxpayer_Marginal_Rate+IF(Tax_Efficient_Status?="State & Federal",State_Income_Tax_Rate,0)) -> 1758.7982 | J67: =J66*(Taxpayer_Marginal_Rate+IF(Tax_Efficient_Status?="State & Federal",State_Income_Tax_Rate,0)) -> 1793.7543 | K67: =K66*(Taxpayer_Marginal_Rate+IF(Tax_Efficient_Status?="State & Federal",State_Income_Tax_Rate,0)) -> 1829.4052 | ... AB67: =AB66*(Taxpayer_Marginal_Rate+IF(Tax_Efficient_Status?="State & Federal",State_Income_Tax_Rate,0)) -> 2556.2775
B68: Owner Tax and Cash | C68: =Unstructured!C87 -> -114975.09 | D68: =Unstructured!D87 -> 39296.835 | E68: =Unstructured!E87 -> 10321.524 | F68: =Unstructured!F87 -> 7770.5867 | G68: =Unstructured!G87 -> 6271.3197 | H68: =Unstructured!H87 -> 6348.8486 | I68: =Unstructured!I87 -> 5246.4495 | J68: =Unstructured!J87 -> 4145.6187 | ... AB68: =Unstructured!AB87 -> 23150.163
B69: Total Benefits | C69: =C68+C67 -> -114975.09 | D69: =D68+D67 -> 40890.809 | E69: =E68+E67 -> 11947.179 | F69: =F68+F67 -> 9428.551 | G69: =G68+G67 -> 7962.2361 | H69: =H68+H67 -> 8073.3719 | I69: =I68+I67 -> 7005.2477 | J69: =J68+J67 -> 5939.373 | ... AB69: =AB68+AB67 -> 25706.441
B70: NPV | C70: =NPV(Customer_Discount_Rate,C68:AB68) -> -6535.8369
B71: IRR | C71: =IRR(C69:AB69) -> 0.080229392
B76: Customer Analysis - Chart Data
B78: After-Tax Owner Customer Economics | D78: 1
B79: Year | C79: 0 | D79: 1 | E79: 2 | F79: 3 | G79: 4 | H79: 5 | I79: 6 | J79: 7 | K79: 8 | L79: 9 | M79: 10 | N79: 11 | O79: 12 | P79: 13 | Q79: 14 | R79: 15 | S79: 16 | T79: 17 | U79: 18 | V79: 19 | W79: 20 | X79: 21 | Y79: 22 | Z79: 23 | AA79: 24 | AB79: 25
B80: Customer Savings | D80: =D27 -> 56.798364 | E80: =E27 -> 57.927232 | F80: =F27 -> 59.078536 | G80: =G27 -> 60.252722 | H80: =H27 -> 61.450244 | I80: =I27 -> 62.671568 | J80: =J27 -> 63.917165 | K80: =K27 -> 65.187519 | ... AB80: =AB27 -> 91.088288
B81: NPV of Customer Savings over 25 Year Term | D81: =D28 -> 876.08977
B83: Net Lifecycle Benefit (Cost)
B84: Year 1 | C84: =C56 -> 0.063471683
B85: Year 7 | C85: =C57 -> 0.059869119
B86: Year 10 | C86: =C58 -> 0.06894082
B87: Year 15 | C87: =C59 -> 0.08348561
B88: Year 20 | C88: =C60 -> 0.096586251
B89: Year 25 | C89: =C61 -> 0.11024272
B91: Current Utility Price | D91: =D22+D23 -> 0.073648296 | E91: =E22+E23 -> 0.075489503 | F91: =F22+F23 -> 0.077376741 | G91: =G22+G23 -> 0.07931116 | H91: =H22+H23 -> 0.081293939 | I91: =I22+I23 -> 0.083326287 | J91: =J22+J23 -> 0.085409444 | K91: =K22+K23 -> 0.08754468 | ... AB91: =AB22+AB23 -> 0.13320958
B92: Est. PPA Price | D92: =D24 -> 0.07303158 | E92: =E24 -> 0.07485737 | F92: =F24 -> 0.076728804 | G92: =G24 -> 0.078647024 | H92: =H24 -> 0.0806132 | I92: =I24 -> 0.08262853 | J92: =J24 -> 0.084694243 | K92: =K24 -> 0.086811599 | ... AB92: =AB24 -> 0.13209411
B94: Utility Purchases | D94: =D19 -> 3860724.9 | E94: =E19 -> 3861185.4 | F94: =F19 -> 3861643.6 | G94: =G19 -> 3862099.5 | H94: =H19 -> 3862553.1 | I94: =I19 -> 3863004.5 | J94: =J19 -> 3863453.6 | K94: =K19 -> 3863900.4 | ... AB94: =AB19 -> 3871163.9
B95: Solar Purchases | D95: =D21 -> 92098.11 | E95: =E21 -> 91637.619 | F95: =F21 -> 91179.431 | G95: =G21 -> 90723.534 | H95: =H21 -> 90269.917 | I95: =I21 -> 89818.567 | J95: =J21 -> 89369.474 | K95: =K21 -> 88922.627 | ... AB95: =AB21 -> 81659.113
